<?xml version="1.0" encoding="UTF-8"?>
<channels>
  <channel site="sky.com" lang="en" xmltv_id="A1TVRajasthan.in" site_id="1104" logo="https://d2n0069hmnqmmx.cloudfront.net/epgdata/1.0/newchanlogos/512/512/skychb1104.png">UK: Islam Bangla</channel>
  <channel site="sky.com" lang="en" xmltv_id="ATNBanglaUK.uk" site_id="6753" logo="https://d2n0069hmnqmmx.cloudfront.net/epgdata/1.0/newchanlogos/512/512/skychb6753.png">UK: ATN</channel>
  <channel site="sky.com" lang="en" xmltv_id="DeenTV.uk" site_id="1235" logo="https://d2n0069hmnqmmx.cloudfront.net/epgdata/1.0/newchanlogos/512/512/skychb1235.png">UK: Deen TV</channel>
  <channel site="sky.com" lang="en" xmltv_id="IqraBangla.uk" site_id="3914" logo="https://d2n0069hmnqmmx.cloudfront.net/epgdata/1.0/newchanlogos/512/512/skychb3914.png">UK: IQRA Bangla</channel>
  <channel site="sky.com" lang="en" xmltv_id="" site_id="1009" logo="https://d2n0069hmnqmmx.cloudfront.net/epgdata/1.0/newchanlogos/512/512/skychb1009.png">UK: QTV Religious</channel>
  <channel site="sky.com" lang="en" xmltv_id="" site_id="1011" logo="https://d2n0069hmnqmmx.cloudfront.net/epgdata/1.0/newchanlogos/512/512/skychb1011.png">UK: PBC</channel>
  <channel site="sky.com" lang="en" xmltv_id="" site_id="1069" logo="https://d2n0069hmnqmmx.cloudfront.net/epgdata/1.0/newchanlogos/512/512/skychb1069.png">UK: HUM Masala</channel>
  <channel site="sky.com" lang="en" xmltv_id="" site_id="1169" logo="https://d2n0069hmnqmmx.cloudfront.net/epgdata/1.0/newchanlogos/512/512/skychb1169.png">UK: HobbyMakerHD</channel>
  <channel site="sky.com" lang="en" xmltv_id="" site_id="1305" logo="https://d2n0069hmnqmmx.cloudfront.net/epgdata/1.0/newchanlogos/512/512/skychb1305.png">UK: Best Xmas Music</channel>
  <channel site="sky.com" lang="en" xmltv_id="" site_id="1361" logo="https://d2n0069hmnqmmx.cloudfront.net/epgdata/1.0/newchanlogos/512/512/skychb1361.png">UK: DAZN PPV HD</channel>
  <channel site="sky.com" lang="en" xmltv_id="" site_id="1819" logo="https://d2n0069hmnqmmx.cloudfront.net/epgdata/1.0/newchanlogos/512/512/skychb1819.png">UK: Sky Intro</channel>
  <channel site="sky.com" lang="en" xmltv_id="" site_id="1852" logo="https://d2n0069hmnqmmx.cloudfront.net/epgdata/1.0/newchanlogos/512/512/skychb1852.png">UK: Sky Intro</channel>
  <channel site="sky.com" lang="en" xmltv_id="" site_id="2601" logo="https://d2n0069hmnqmmx.cloudfront.net/epgdata/1.0/newchanlogos/512/512/skychb2601.png">UK: SONY TV</channel>
  <channel site="sky.com" lang="en" xmltv_id="" site_id="3117" logo="https://d2n0069hmnqmmx.cloudfront.net/epgdata/1.0/newchanlogos/512/512/skychb3117.png">UK: EWTN Catholic</channel>
  <channel site="sky.com" lang="en" xmltv_id="" site_id="3202" logo="https://d2n0069hmnqmmx.cloudfront.net/epgdata/1.0/newchanlogos/512/512/skychb3202.png">UK: MTA1 World HD</channel>
  <channel site="sky.com" lang="en" xmltv_id="" site_id="3352" logo="https://d2n0069hmnqmmx.cloudfront.net/epgdata/1.0/newchanlogos/512/512/skychb3352.png">UK: TRUE CRIME</channel>
  <channel site="sky.com" lang="en" xmltv_id="" site_id="3392" logo="https://d2n0069hmnqmmx.cloudfront.net/epgdata/1.0/newchanlogos/512/512/skychb3392.png">UK: SonLife</channel>
  <channel site="sky.com" lang="en" xmltv_id="" site_id="3731" logo="https://d2n0069hmnqmmx.cloudfront.net/epgdata/1.0/newchanlogos/512/512/skychb3731.png">UK: NTD</channel>
  <channel site="sky.com" lang="en" xmltv_id="" site_id="3815" logo="https://d2n0069hmnqmmx.cloudfront.net/epgdata/1.0/newchanlogos/512/512/skychb3815.png">UK: CHSTV</channel>
  <channel site="sky.com" lang="en" xmltv_id="" site_id="4540" logo="https://d2n0069hmnqmmx.cloudfront.net/epgdata/1.0/newchanlogos/512/512/skychb4540.png">UK: NTV</channel>
  <channel site="sky.com" lang="en" xmltv_id="4Music.uk" site_id="1350" logo="https://d2n0069hmnqmmx.cloudfront.net/epgdata/1.0/newchanlogos/512/512/skychb1350.png">UK: 4Music</channel>
  <channel site="sky.com" lang="en" xmltv_id="4seven.uk" site_id="3150" logo="https://d2n0069hmnqmmx.cloudfront.net/epgdata/1.0/newchanlogos/512/512/skychb3150.png">UK: 4seven</channel>
  <channel site="sky.com" lang="en" xmltv_id="5Action.uk" site_id="1036" logo="https://d2n0069hmnqmmx.cloudfront.net/epgdata/1.0/newchanlogos/512/512/skychb1036.png">UK: 5ACTION</channel>
  <channel site="sky.com" lang="en" xmltv_id="5SELECT.uk" site_id="3028" logo="https://d2n0069hmnqmmx.cloudfront.net/epgdata/1.0/newchanlogos/512/512/skychb3028.png">UK: 5SELECT</channel>
  <channel site="sky.com" lang="en" xmltv_id="5STAR.uk" site_id="3023" logo="https://d2n0069hmnqmmx.cloudfront.net/epgdata/1.0/newchanlogos/512/512/skychb3023.png">UK: 5STAR</channel>
  <channel site="sky.com" lang="en" xmltv_id="5STARPlus1.uk" site_id="3024" logo="https://d2n0069hmnqmmx.cloudfront.net/epgdata/1.0/newchanlogos/512/512/skychb3024.png">UK: 5STAR+1</channel>
  <channel site="sky.com" lang="en" xmltv_id="5USA.uk" site_id="3022" logo="https://d2n0069hmnqmmx.cloudfront.net/epgdata/1.0/newchanlogos/512/512/skychb3022.png">UK: 5 USA</channel>
  <channel site="sky.com" lang="en" xmltv_id="5USAPlus1.uk" site_id="3027" logo="https://d2n0069hmnqmmx.cloudfront.net/epgdata/1.0/newchanlogos/512/512/skychb3027.png">UK: 5USA+1</channel>
  <channel site="sky.com" lang="en" xmltv_id="AhlebaitTV.uk" site_id="6765" logo="https://d2n0069hmnqmmx.cloudfront.net/epgdata/1.0/newchanlogos/512/512/skychb6765.png">UK: Ahlebait TV</channel>
  <channel site="sky.com" lang="en" xmltv_id="AkaalChannel.uk" site_id="5087" logo="https://d2n0069hmnqmmx.cloudfront.net/epgdata/1.0/newchanlogos/512/512/skychb5087.png">UK: Akaal Channel</channel>
  <channel site="sky.com" lang="en" xmltv_id="alibi.uk" site_id="2303" logo="https://d2n0069hmnqmmx.cloudfront.net/epgdata/1.0/newchanlogos/512/512/skychb2303.png">UK: alibi</channel>
  <channel site="sky.com" lang="en" xmltv_id="alibiHD.uk" site_id="3825" logo="https://d2n0069hmnqmmx.cloudfront.net/epgdata/1.0/newchanlogos/512/512/skychb3825.png">UK: alibi HD</channel>
  <channel site="sky.com" lang="en" xmltv_id="alibiPlus1.uk" site_id="2630" logo="https://d2n0069hmnqmmx.cloudfront.net/epgdata/1.0/newchanlogos/512/512/skychb2630.png">UK: alibi+1</channel>
  <channel site="sky.com" lang="en" xmltv_id="AlJazeeraEnglish.qa" site_id="1023" logo="https://d2n0069hmnqmmx.cloudfront.net/epgdata/1.0/newchanlogos/512/512/skychb1023.png">UK: Al Jazeera HD</channel>
  <channel site="sky.com" lang="en" xmltv_id="AnimalPlanet.uk" site_id="2402" logo="https://d2n0069hmnqmmx.cloudfront.net/epgdata/1.0/newchanlogos/512/512/skychb2402.png">UK: Animal Planet</channel>
  <channel site="sky.com" lang="en" xmltv_id="AnimalPlanetPlus1.uk" site_id="1352" logo="https://d2n0069hmnqmmx.cloudfront.net/epgdata/1.0/newchanlogos/512/512/skychb1352.png">UK: Animal Plnt+1</channel>
  <channel site="sky.com" lang="en" xmltv_id="ArirangWorld.kr" site_id="1066" logo="https://d2n0069hmnqmmx.cloudfront.net/epgdata/1.0/newchanlogos/512/512/skychb1066.png">UK: Arirang TV HD</channel>
  <channel site="sky.com" lang="en" xmltv_id="AriseNews.uk" site_id="5040" logo="https://d2n0069hmnqmmx.cloudfront.net/epgdata/1.0/newchanlogos/512/512/skychb5040.png">UK: Arise News</channel>
  <channel site="sky.com" lang="en" xmltv_id="AyozatTV.uk" site_id="3206" logo="https://d2n0069hmnqmmx.cloudfront.net/epgdata/1.0/newchanlogos/512/512/skychb3206.png">UK: Ayozat TV</channel>
  <channel site="sky.com" lang="en" xmltv_id="BabyTV.uk" site_id="3645" logo="https://d2n0069hmnqmmx.cloudfront.net/epgdata/1.0/newchanlogos/512/512/skychb3645.png">UK: BabyTV</channel>
  <channel site="sky.com" lang="en" xmltv_id="BBCALBA.uk" site_id="2012" logo="https://d2n0069hmnqmmx.cloudfront.net/epgdata/1.0/newchanlogos/512/512/skychb2012.png">UK: BBC ALBA</channel>
  <channel site="sky.com" lang="en" xmltv_id="BBCALBAHD.uk" site_id="3021" logo="https://d2n0069hmnqmmx.cloudfront.net/epgdata/1.0/newchanlogos/512/512/skychb3021.png">UK: BBC ALBA HD</channel>
  <channel site="sky.com" lang="en" xmltv_id="BBCFour.uk" site_id="2018" logo="https://d2n0069hmnqmmx.cloudfront.net/epgdata/1.0/newchanlogos/512/512/skychb2018.png">UK: BBC Four</channel>
  <channel site="sky.com" lang="en" xmltv_id="BBCFourHD.uk" site_id="2086" logo="https://d2n0069hmnqmmx.cloudfront.net/epgdata/1.0/newchanlogos/512/512/skychb2086.png">UK: BBC Four HD</channel>
  <channel site="sky.com" lang="en" xmltv_id="BBCNews.uk" site_id="2011" logo="https://d2n0069hmnqmmx.cloudfront.net/epgdata/1.0/newchanlogos/512/512/skychb2011.png">UK: BBC NEWS</channel>
  <channel site="sky.com" lang="en" xmltv_id="BBCNewsHD.uk" site_id="2085" logo="https://d2n0069hmnqmmx.cloudfront.net/epgdata/1.0/newchanlogos/512/512/skychb2085.png">UK: BBC NEWS HD</channel>
  <channel site="sky.com" lang="en" xmltv_id="BBCOne.uk" site_id="1006" logo="https://d2n0069hmnqmmx.cloudfront.net/epgdata/1.0/newchanlogos/512/512/skychb1006.png">UK: BBC One</channel>
  <channel site="sky.com" lang="en" xmltv_id="BBCOneChannelIslandsHD.uk" site_id="3018" logo="https://d2n0069hmnqmmx.cloudfront.net/epgdata/1.0/newchanlogos/512/512/skychb3018.png">UK: BBC One CI HD</channel>
  <channel site="sky.com" lang="en" xmltv_id="BBCOneEastHD.uk" site_id="3006" logo="https://d2n0069hmnqmmx.cloudfront.net/epgdata/1.0/newchanlogos/512/512/skychb3006.png">UK: BBC One EastHD</channel>
  <channel site="sky.com" lang="en" xmltv_id="BBCOneEastMidlandsHD.uk" site_id="3005" logo="https://d2n0069hmnqmmx.cloudfront.net/epgdata/1.0/newchanlogos/512/512/skychb3005.png">UK: BBC One EMidHD</channel>
  <channel site="sky.com" lang="en" xmltv_id="BBCOneLondonHD.uk" site_id="3000" logo="https://d2n0069hmnqmmx.cloudfront.net/epgdata/1.0/newchanlogos/512/512/skychb3000.png">UK: BBC One Lon HD</channel>
  <channel site="sky.com" lang="en" xmltv_id="BBCOneNorthEastCumbriaHD.uk" site_id="3009" logo="https://d2n0069hmnqmmx.cloudfront.net/epgdata/1.0/newchanlogos/512/512/skychb3009.png">UK: BBC One NE HD</channel>
  <channel site="sky.com" lang="en" xmltv_id="BBCOneNorthernIrelandHD.uk" site_id="2081" logo="https://d2n0069hmnqmmx.cloudfront.net/epgdata/1.0/newchanlogos/512/512/skychb2081.png">UK: BBC One NI HD</channel>
  <channel site="sky.com" lang="en" xmltv_id="BBCOneNorthWestHD.uk" site_id="3007" logo="https://d2n0069hmnqmmx.cloudfront.net/epgdata/1.0/newchanlogos/512/512/skychb3007.png">UK: BBC One NW HD</channel>
  <channel site="sky.com" lang="en" xmltv_id="BBCOneScotlandHD.uk" site_id="2082" logo="https://d2n0069hmnqmmx.cloudfront.net/epgdata/1.0/newchanlogos/512/512/skychb2082.png">UK: BBC One ScotHD</channel>
  <channel site="sky.com" lang="en" xmltv_id="BBCOneSouthEastHD.uk" site_id="3008" logo="https://d2n0069hmnqmmx.cloudfront.net/epgdata/1.0/newchanlogos/512/512/skychb3008.png">UK: BBC One SE HD</channel>
  <channel site="sky.com" lang="en" xmltv_id="BBCOneSouthHD.uk" site_id="3011" logo="https://d2n0069hmnqmmx.cloudfront.net/epgdata/1.0/newchanlogos/512/512/skychb3011.png">UK: BBC One Sth HD</channel>
  <channel site="sky.com" lang="en" xmltv_id="BBCOneSouthWestHD.uk" site_id="3014" logo="https://d2n0069hmnqmmx.cloudfront.net/epgdata/1.0/newchanlogos/512/512/skychb3014.png">UK: BBC One SW HD</channel>
  <channel site="sky.com" lang="en" xmltv_id="BBCOneWalesHD.uk" site_id="2083" logo="https://d2n0069hmnqmmx.cloudfront.net/epgdata/1.0/newchanlogos/512/512/skychb2083.png">UK: BBC One Wal HD</channel>
  <channel site="sky.com" lang="en" xmltv_id="BBCOneWestHD.uk" site_id="3001" logo="https://d2n0069hmnqmmx.cloudfront.net/epgdata/1.0/newchanlogos/512/512/skychb3001.png">UK: BBC One Wst HD</channel>
  <channel site="sky.com" lang="en" xmltv_id="BBCOneWestMidlandsHD.uk" site_id="3003" logo="https://d2n0069hmnqmmx.cloudfront.net/epgdata/1.0/newchanlogos/512/512/skychb3003.png">UK: BBC One WM HD</channel>
  <channel site="sky.com" lang="en" xmltv_id="BBCOneYorkshireHD.uk" site_id="3017" logo="https://d2n0069hmnqmmx.cloudfront.net/epgdata/1.0/newchanlogos/512/512/skychb3017.png">UK: BBC One Yks HD</channel>
  <channel site="sky.com" lang="en" xmltv_id="BBCOneYorkshireLincolnshireHD.uk" site_id="3004" logo="https://d2n0069hmnqmmx.cloudfront.net/epgdata/1.0/newchanlogos/512/512/skychb3004.png">UK: BBC One Y&amp;L HD</channel>
  <channel site="sky.com" lang="en" xmltv_id="BBCParliament.uk" site_id="2072" logo="https://d2n0069hmnqmmx.cloudfront.net/epgdata/1.0/newchanlogos/512/512/skychb2072.png">UK: BBC Parliament</channel>
  <channel site="sky.com" lang="en" xmltv_id="BBCParliamentHD.uk" site_id="3020" logo="https://d2n0069hmnqmmx.cloudfront.net/epgdata/1.0/newchanlogos/512/512/skychb3020.png">UK: BBC Parl HD</channel>
  <channel site="sky.com" lang="en" xmltv_id="BBCRedButton1.uk" site_id="2051" logo="https://d2n0069hmnqmmx.cloudfront.net/epgdata/1.0/newchanlogos/512/512/skychb2051.png">UK: BBC RB 1</channel>
  <channel site="sky.com" lang="en" xmltv_id="BBCRedButton1HD.uk" site_id="2053" logo="https://d2n0069hmnqmmx.cloudfront.net/epgdata/1.0/newchanlogos/512/512/skychb2053.png">UK: BBC RB 1 HD</channel>
  <channel site="sky.com" lang="en" xmltv_id="BBCScotland.uk" site_id="1137" logo="https://d2n0069hmnqmmx.cloudfront.net/epgdata/1.0/newchanlogos/512/512/skychb1137.png">UK: BBC Scotland</channel>
  <channel site="sky.com" lang="en" xmltv_id="BBCScotlandHD.uk" site_id="1138" logo="https://d2n0069hmnqmmx.cloudfront.net/epgdata/1.0/newchanlogos/512/512/skychb1138.png">UK: BBCScotlandHD</channel>
  <channel site="sky.com" lang="en" xmltv_id="BBCThree.uk" site_id="2022" logo="https://d2n0069hmnqmmx.cloudfront.net/epgdata/1.0/newchanlogos/512/512/skychb2022.png">UK: BBC Three</channel>
  <channel site="sky.com" lang="en" xmltv_id="BBCThreeHD.uk" site_id="2080" logo="https://d2n0069hmnqmmx.cloudfront.net/epgdata/1.0/newchanlogos/512/512/skychb2080.png">UK: BBC Three HD</channel>
  <channel site="sky.com" lang="en" xmltv_id="BBCTwo.uk" site_id="2006" logo="https://d2n0069hmnqmmx.cloudfront.net/epgdata/1.0/newchanlogos/512/512/skychb2006.png">UK: BBC Two</channel>
  <channel site="sky.com" lang="en" xmltv_id="BBCTwoHD.uk" site_id="2075" logo="https://d2n0069hmnqmmx.cloudfront.net/epgdata/1.0/newchanlogos/512/512/skychb2075.png">UK: BBC Two HD</channel>
  <channel site="sky.com" lang="en" xmltv_id="BBCTwoNorthernIrelandHD.uk" site_id="3019" logo="https://d2n0069hmnqmmx.cloudfront.net/epgdata/1.0/newchanlogos/512/512/skychb3019.png">UK: BBC Two NI HD</channel>
  <channel site="sky.com" lang="en" xmltv_id="BBCTwoWalesHD.uk" site_id="3015" logo="https://d2n0069hmnqmmx.cloudfront.net/epgdata/1.0/newchanlogos/512/512/skychb3015.png">UK: BBC Two Wal HD</channel>
  <channel site="sky.com" lang="en" xmltv_id="BestDirect.uk" site_id="4100" logo="https://d2n0069hmnqmmx.cloudfront.net/epgdata/1.0/newchanlogos/512/512/skychb4100.png">UK: Best Direct</channel>
  <channel site="sky.com" lang="en" xmltv_id="Blaze.uk" site_id="1065" logo="https://d2n0069hmnqmmx.cloudfront.net/epgdata/1.0/newchanlogos/512/512/skychb1065.png">UK: BLAZE</channel>
  <channel site="sky.com" lang="en" xmltv_id="BloombergTVEurope.uk" site_id="1074" logo="https://d2n0069hmnqmmx.cloudfront.net/epgdata/1.0/newchanlogos/512/512/skychb1074.png">UK: Bloomberg HD</channel>
  <channel site="sky.com" lang="en" xmltv_id="Boomerang.uk" site_id="5609" logo="https://d2n0069hmnqmmx.cloudfront.net/epgdata/1.0/newchanlogos/512/512/skychb5609.png">UK: Boomerang</channel>
  <channel site="sky.com" lang="en" xmltv_id="BoomerangHD.uk" site_id="4030" logo="https://d2n0069hmnqmmx.cloudfront.net/epgdata/1.0/newchanlogos/512/512/skychb4030.png">UK: Boomerang HD</channel>
  <channel site="sky.com" lang="en" xmltv_id="BoomerangPlus1.uk" site_id="5603" logo="https://d2n0069hmnqmmx.cloudfront.net/epgdata/1.0/newchanlogos/512/512/skychb5603.png">UK: Boomerang+1</channel>
  <channel site="sky.com" lang="en" xmltv_id="BritAsiaTV.uk" site_id="3653" logo="https://d2n0069hmnqmmx.cloudfront.net/epgdata/1.0/newchanlogos/512/512/skychb3653.png">UK: Brit Asia TV</channel>
  <channel site="sky.com" lang="en" xmltv_id="BritishMuslimTV.uk" site_id="5417" logo="https://d2n0069hmnqmmx.cloudfront.net/epgdata/1.0/newchanlogos/512/512/skychb5417.png">UK: British Muslim</channel>
  <channel site="sky.com" lang="en" xmltv_id="Cartoonito.uk" site_id="1371" logo="https://d2n0069hmnqmmx.cloudfront.net/epgdata/1.0/newchanlogos/512/512/skychb1371.png">UK: Cartoonito</channel>
  <channel site="sky.com" lang="en" xmltv_id="CartoonNetwork.uk" site_id="4077" logo="https://d2n0069hmnqmmx.cloudfront.net/epgdata/1.0/newchanlogos/512/512/skychb4077.png">UK: Cartoon Net HD</channel>
  <channel site="sky.com" lang="en" xmltv_id="CartoonNetwork.uk" site_id="5601" logo="https://d2n0069hmnqmmx.cloudfront.net/epgdata/1.0/newchanlogos/512/512/skychb5601.png">UK: Cartoon Netwrk</channel>
  <channel site="sky.com" lang="en" xmltv_id="CartoonNetworkPlus1.uk" site_id="5610" logo="https://d2n0069hmnqmmx.cloudfront.net/epgdata/1.0/newchanlogos/512/512/skychb5610.png">UK: CN+1</channel>
  <channel site="sky.com" lang="en" xmltv_id="CBBC.uk" site_id="2020" logo="https://d2n0069hmnqmmx.cloudfront.net/epgdata/1.0/newchanlogos/512/512/skychb2020.png">UK: CBBC</channel>
  <channel site="sky.com" lang="en" xmltv_id="CBBCHD.uk" site_id="2078" logo="https://d2n0069hmnqmmx.cloudfront.net/epgdata/1.0/newchanlogos/512/512/skychb2078.png">UK: CBBC HD</channel>
  <channel site="sky.com" lang="en" xmltv_id="CBeebies.uk" site_id="2019" logo="https://d2n0069hmnqmmx.cloudfront.net/epgdata/1.0/newchanlogos/512/512/skychb2019.png">UK: CBeebies</channel>
  <channel site="sky.com" lang="en" xmltv_id="CBeebiesHD.uk" site_id="2088" logo="https://d2n0069hmnqmmx.cloudfront.net/epgdata/1.0/newchanlogos/512/512/skychb2088.png">UK: CBeebies HD</channel>
  <channel site="sky.com" lang="en" xmltv_id="CBSRealityPlus1.uk" site_id="3602" logo="https://d2n0069hmnqmmx.cloudfront.net/epgdata/1.0/newchanlogos/512/512/skychb3602.png">UK: TRUE CRIME+1</channel>
  <channel site="sky.com" lang="en" xmltv_id="Challenge.uk" site_id="2202" logo="https://d2n0069hmnqmmx.cloudfront.net/epgdata/1.0/newchanlogos/512/512/skychb2202.png">UK: Challenge</channel>
  <channel site="sky.com" lang="en" xmltv_id="Channel4.uk" site_id="1621" logo="https://d2n0069hmnqmmx.cloudfront.net/epgdata/1.0/newchanlogos/512/512/skychb1621.png">UK: Channel 4</channel>
  <channel site="sky.com" lang="en" xmltv_id="Channel4HD.uk" site_id="4075" logo="https://d2n0069hmnqmmx.cloudfront.net/epgdata/1.0/newchanlogos/512/512/skychb4075.png">UK: Channel 4 HD</channel>
  <channel site="sky.com" lang="en" xmltv_id="Channel4Plus1.uk" site_id="1670" logo="https://d2n0069hmnqmmx.cloudfront.net/epgdata/1.0/newchanlogos/512/512/skychb1670.png">UK: Channel 4+1</channel>
  <channel site="sky.com" lang="en" xmltv_id="Channel5.uk" site_id="1800" logo="https://d2n0069hmnqmmx.cloudfront.net/epgdata/1.0/newchanlogos/512/512/skychb1800.png">UK: Channel 5</channel>
  <channel site="sky.com" lang="en" xmltv_id="Channel5HD.uk" site_id="4058" logo="https://d2n0069hmnqmmx.cloudfront.net/epgdata/1.0/newchanlogos/512/512/skychb4058.png">UK: Channel 5 HD</channel>
  <channel site="sky.com" lang="en" xmltv_id="Channel5Plus1.uk" site_id="1839" logo="https://d2n0069hmnqmmx.cloudfront.net/epgdata/1.0/newchanlogos/512/512/skychb1839.png">UK: Channel 5+1</channel>
  <channel site="sky.com" lang="en" xmltv_id="Channel7TV.uk" site_id="3687" logo="https://d2n0069hmnqmmx.cloudfront.net/epgdata/1.0/newchanlogos/512/512/skychb3687.png">UK: Channel 7</channel>
  <channel site="sky.com" lang="en" xmltv_id="Channels24.ng" site_id="5520" logo="https://d2n0069hmnqmmx.cloudfront.net/epgdata/1.0/newchanlogos/512/512/skychb5520.png">UK: Channels 24</channel>
  <channel site="sky.com" lang="en" xmltv_id="ClublandTV.uk" site_id="4505" logo="https://d2n0069hmnqmmx.cloudfront.net/epgdata/1.0/newchanlogos/512/512/skychb4505.png">UK: Clubland TV</channel>
  <channel site="sky.com" lang="en" xmltv_id="CNBCEurope.uk" site_id="1088" logo="https://d2n0069hmnqmmx.cloudfront.net/epgdata/1.0/newchanlogos/512/512/skychb1088.png">UK: CNBC HD</channel>
  <channel site="sky.com" lang="en" xmltv_id="CNNInternationalEuropeHD.us" site_id="1019" logo="https://d2n0069hmnqmmx.cloudfront.net/epgdata/1.0/newchanlogos/512/512/skychb1019.png">UK: CNN HD</channel>
  <channel site="sky.com" lang="en" xmltv_id="ColorsMENAHD.in" site_id="1372" logo="https://d2n0069hmnqmmx.cloudfront.net/epgdata/1.0/newchanlogos/512/512/skychb1372.png">UK: COLORS HD</channel>
  <channel site="sky.com" lang="en" xmltv_id="ComedyCentral.uk" site_id="2510" logo="https://d2n0069hmnqmmx.cloudfront.net/epgdata/1.0/newchanlogos/512/512/skychb2510.png">UK: ComedyCentral</channel>
  <channel site="sky.com" lang="en" xmltv_id="ComedyCentralExtra.uk" site_id="1813" logo="https://d2n0069hmnqmmx.cloudfront.net/epgdata/1.0/newchanlogos/512/512/skychb1813.png">UK: ComedyXtra</channel>
  <channel site="sky.com" lang="en" xmltv_id="ComedyCentralHD.uk" site_id="4056" logo="https://d2n0069hmnqmmx.cloudfront.net/epgdata/1.0/newchanlogos/512/512/skychb4056.png">UK: ComedyCentHD</channel>
  <channel site="sky.com" lang="en" xmltv_id="ComedyCentralPlus1.uk" site_id="3802" logo="https://d2n0069hmnqmmx.cloudfront.net/epgdata/1.0/newchanlogos/512/512/skychb3802.png">UK: ComedyCent+1</channel>
  <channel site="sky.com" lang="en" xmltv_id="CourtTV.uk" site_id="1207" logo="https://d2n0069hmnqmmx.cloudfront.net/epgdata/1.0/newchanlogos/512/512/skychb1207.png">UK: Court TV</channel>
  <channel site="sky.com" lang="en" xmltv_id="CraftExtra.uk" site_id="3357" logo="https://d2n0069hmnqmmx.cloudfront.net/epgdata/1.0/newchanlogos/512/512/skychb3357.png">UK: Craft Extra</channel>
  <channel site="sky.com" lang="en" xmltv_id="CreateandCraft.uk" site_id="1245" logo="https://d2n0069hmnqmmx.cloudfront.net/epgdata/1.0/newchanlogos/512/512/skychb1245.png">UK: Create&amp;CraftHD</channel>
  <channel site="sky.com" lang="en" xmltv_id="CrimePlusInvestigation.uk" site_id="1448" logo="https://d2n0069hmnqmmx.cloudfront.net/epgdata/1.0/newchanlogos/512/512/skychb1448.png">UK: Crime+Inv</channel>
  <channel site="sky.com" lang="en" xmltv_id="CrimePlusInvestigationHD.uk" site_id="4088" logo="https://d2n0069hmnqmmx.cloudfront.net/epgdata/1.0/newchanlogos/512/512/skychb4088.png">UK: Crime+Inv HD</channel>
  <channel site="sky.com" lang="en" xmltv_id="CrimePlusInvestigationPlus1.uk" site_id="3620" logo="https://d2n0069hmnqmmx.cloudfront.net/epgdata/1.0/newchanlogos/512/512/skychb3620.png">UK: Crime+Inv+1</channel>
  <channel site="sky.com" lang="en" xmltv_id="Cruise1stTV.uk" site_id="1018" logo="https://d2n0069hmnqmmx.cloudfront.net/epgdata/1.0/newchanlogos/512/512/skychb1018.png">UK: Cruise1st.tv</channel>
  <channel site="sky.com" lang="en" xmltv_id="Dave.uk" site_id="2306" logo="https://d2n0069hmnqmmx.cloudfront.net/epgdata/1.0/newchanlogos/512/512/skychb2306.png">UK: Dave</channel>
  <channel site="sky.com" lang="en" xmltv_id="DaveHD.uk" site_id="3809" logo="https://d2n0069hmnqmmx.cloudfront.net/epgdata/1.0/newchanlogos/512/512/skychb3809.png">UK: Dave HD</channel>
  <channel site="sky.com" lang="en" xmltv_id="Davejavu.uk" site_id="2320" logo="https://d2n0069hmnqmmx.cloudfront.net/epgdata/1.0/newchanlogos/512/512/skychb2320.png">UK: Dave ja vu</channel>
  <channel site="sky.com" lang="en" xmltv_id="DaystarTV.us" site_id="5541" logo="https://d2n0069hmnqmmx.cloudfront.net/epgdata/1.0/newchanlogos/512/512/skychb5541.png">UK: DAYSTAR HD</channel>
  <channel site="sky.com" lang="en" xmltv_id="DAZN1HD.uk" site_id="1359" logo="https://d2n0069hmnqmmx.cloudfront.net/epgdata/1.0/newchanlogos/512/512/skychb1359.png">UK: DAZN 1 HD</channel>
  <channel site="sky.com" lang="en" xmltv_id="DirectStoreTV.uk" site_id="3415" logo="https://d2n0069hmnqmmx.cloudfront.net/epgdata/1.0/newchanlogos/512/512/skychb3415.png">UK: Direct Store TV</channel>
  <channel site="sky.com" lang="en" xmltv_id="DiscoveryChannel.uk" site_id="2401" logo="https://d2n0069hmnqmmx.cloudfront.net/epgdata/1.0/newchanlogos/512/512/skychb2401.png">UK: Discovery</channel>
  <channel site="sky.com" lang="en" xmltv_id="DiscoveryChannel.uk" site_id="4003" logo="https://d2n0069hmnqmmx.cloudfront.net/epgdata/1.0/newchanlogos/512/512/skychb4003.png">UK: Discovery HD</channel>
  <channel site="sky.com" lang="en" xmltv_id="DiscoveryChannelPlus1.uk" site_id="2404" logo="https://d2n0069hmnqmmx.cloudfront.net/epgdata/1.0/newchanlogos/512/512/skychb2404.png">UK: Discovery+1</channel>
  <channel site="sky.com" lang="en" xmltv_id="DiscoveryHistory.uk" site_id="2407" logo="https://d2n0069hmnqmmx.cloudfront.net/epgdata/1.0/newchanlogos/512/512/skychb2407.png">UK: Disc.History</channel>
  <channel site="sky.com" lang="en" xmltv_id="DiscoveryHistoryPlus1.uk" site_id="3760" logo="https://d2n0069hmnqmmx.cloudfront.net/epgdata/1.0/newchanlogos/512/512/skychb3760.png">UK: Disc.History+1</channel>
  <channel site="sky.com" lang="en" xmltv_id="DiscoveryScience.uk" site_id="2406" logo="https://d2n0069hmnqmmx.cloudfront.net/epgdata/1.0/newchanlogos/512/512/skychb2406.png">UK: Disc.Science</channel>
  <channel site="sky.com" lang="en" xmltv_id="DiscoverySciencePlus1.uk" site_id="1351" logo="https://d2n0069hmnqmmx.cloudfront.net/epgdata/1.0/newchanlogos/512/512/skychb1351.png">UK: Disc.Sci+1</channel>
  <channel site="sky.com" lang="en" xmltv_id="DiscoveryTurbo.uk" site_id="2409" logo="https://d2n0069hmnqmmx.cloudfront.net/epgdata/1.0/newchanlogos/512/512/skychb2409.png">UK: Disc.Turbo</channel>
  <channel site="sky.com" lang="en" xmltv_id="DiscoveryTurboPlus1.uk" site_id="5245" logo="https://d2n0069hmnqmmx.cloudfront.net/epgdata/1.0/newchanlogos/512/512/skychb5245.png">UK: Disc.Turbo+1</channel>
  <channel site="sky.com" lang="en" xmltv_id="DMAX.uk" site_id="3618" logo="https://d2n0069hmnqmmx.cloudfront.net/epgdata/1.0/newchanlogos/512/512/skychb3618.png">UK: DMAX</channel>
  <channel site="sky.com" lang="en" xmltv_id="DMAXPlus1.uk" site_id="1865" logo="https://d2n0069hmnqmmx.cloudfront.net/epgdata/1.0/newchanlogos/512/512/skychb1865.png">UK: DMAX+1</channel>
  <channel site="sky.com" lang="en" xmltv_id="Drama.uk" site_id="2612" logo="https://d2n0069hmnqmmx.cloudfront.net/epgdata/1.0/newchanlogos/512/512/skychb2612.png">UK: Drama</channel>
  <channel site="sky.com" lang="en" xmltv_id="DramaPlus1.uk" site_id="1081" logo="https://d2n0069hmnqmmx.cloudfront.net/epgdata/1.0/newchanlogos/512/512/skychb1081.png">UK: Drama+1</channel>
  <channel site="sky.com" lang="en" xmltv_id="DunamisTV.ng" site_id="1191" logo="https://d2n0069hmnqmmx.cloudfront.net/epgdata/1.0/newchanlogos/512/512/skychb1191.png">UK: Dunamis TV</channel>
  <channel site="sky.com" lang="en" xmltv_id="DunyaNews.pk" site_id="1038" logo="https://d2n0069hmnqmmx.cloudfront.net/epgdata/1.0/newchanlogos/512/512/skychb1038.png">UK: Dunya News</channel>
  <channel site="sky.com" lang="en" xmltv_id="E.uk" site_id="1360" logo="https://d2n0069hmnqmmx.cloudfront.net/epgdata/1.0/newchanlogos/512/512/skychb1360.png">UK: E!</channel>
  <channel site="sky.com" lang="en" xmltv_id="E4.uk" site_id="1628" logo="https://d2n0069hmnqmmx.cloudfront.net/epgdata/1.0/newchanlogos/512/512/skychb1628.png">UK: E4</channel>
  <channel site="sky.com" lang="en" xmltv_id="E4Extra.uk" site_id="1758" logo="https://d2n0069hmnqmmx.cloudfront.net/epgdata/1.0/newchanlogos/512/512/skychb1758.png">UK: E4 Extra</channel>
  <channel site="sky.com" lang="en" xmltv_id="E4HD.uk" site_id="4076" logo="https://d2n0069hmnqmmx.cloudfront.net/epgdata/1.0/newchanlogos/512/512/skychb4076.png">UK: E4 HD</channel>
  <channel site="sky.com" lang="en" xmltv_id="E4Plus1.uk" site_id="3300" logo="https://d2n0069hmnqmmx.cloudfront.net/epgdata/1.0/newchanlogos/512/512/skychb3300.png">UK: E4+1</channel>
  <channel site="sky.com" lang="en" xmltv_id="EarthxTV.us" site_id="1086" logo="https://d2n0069hmnqmmx.cloudfront.net/epgdata/1.0/newchanlogos/512/512/skychb1086.png">UK: EarthxTV HD</channel>
  <channel site="sky.com" lang="en" xmltv_id="Eden.uk" site_id="2302" logo="https://d2n0069hmnqmmx.cloudfront.net/epgdata/1.0/newchanlogos/512/512/skychb2302.png">UK: Eden</channel>
  <channel site="sky.com" lang="en" xmltv_id="EdenPlus1.uk" site_id="2307" logo="https://d2n0069hmnqmmx.cloudfront.net/epgdata/1.0/newchanlogos/512/512/skychb2307.png">UK: Eden+1</channel>
  <channel site="sky.com" lang="en" xmltv_id="EHD.uk" site_id="4028" logo="https://d2n0069hmnqmmx.cloudfront.net/epgdata/1.0/newchanlogos/512/512/skychb4028.png">UK: E! HD</channel>
  <channel site="sky.com" lang="en" xmltv_id="EmanChannel.uk" site_id="3111" logo="https://d2n0069hmnqmmx.cloudfront.net/epgdata/1.0/newchanlogos/512/512/skychb3111.png">UK: Eman Channel</channel>
  <channel site="sky.com" lang="en" xmltv_id="EuronewsEnglish.fr" site_id="4604" logo="https://d2n0069hmnqmmx.cloudfront.net/epgdata/1.0/newchanlogos/512/512/skychb4604.png">UK: Euronews</channel>
  <channel site="sky.com" lang="en" xmltv_id="Eurosport1.uk" site_id="1726" logo="https://d2n0069hmnqmmx.cloudfront.net/epgdata/1.0/newchanlogos/512/512/skychb1726.png">UK: Eurosport 1</channel>
  <channel site="sky.com" lang="en" xmltv_id="Eurosport1HD.uk" site_id="4004" logo="https://d2n0069hmnqmmx.cloudfront.net/epgdata/1.0/newchanlogos/512/512/skychb4004.png">UK: Eurosport 1 HD</channel>
  <channel site="sky.com" lang="en" xmltv_id="Eurosport2.uk" site_id="1841" logo="https://d2n0069hmnqmmx.cloudfront.net/epgdata/1.0/newchanlogos/512/512/skychb1841.png">UK: Eurosport 2</channel>
  <channel site="sky.com" lang="en" xmltv_id="Eurosport2HD.uk" site_id="4009" logo="https://d2n0069hmnqmmx.cloudfront.net/epgdata/1.0/newchanlogos/512/512/skychb4009.png">UK: Eurosport 2 HD</channel>
  <channel site="sky.com" lang="en" xmltv_id="FaithUK.uk" site_id="5354" logo="https://d2n0069hmnqmmx.cloudfront.net/epgdata/1.0/newchanlogos/512/512/skychb5354.png">UK: Faith UK</channel>
  <channel site="sky.com" lang="en" xmltv_id="FaithWorldTV.uk" site_id="4404" logo="https://d2n0069hmnqmmx.cloudfront.net/epgdata/1.0/newchanlogos/512/512/skychb4404.png">UK: Faith World TV</channel>
  <channel site="sky.com" lang="en" xmltv_id="Film4.uk" site_id="1627" logo="https://d2n0069hmnqmmx.cloudfront.net/epgdata/1.0/newchanlogos/512/512/skychb1627.png">UK: Film4</channel>
  <channel site="sky.com" lang="en" xmltv_id="Film4HD.uk" site_id="4044" logo="https://d2n0069hmnqmmx.cloudfront.net/epgdata/1.0/newchanlogos/512/512/skychb4044.png">UK: Film4 HD</channel>
  <channel site="sky.com" lang="en" xmltv_id="Film4Plus1.uk" site_id="1629" logo="https://d2n0069hmnqmmx.cloudfront.net/epgdata/1.0/newchanlogos/512/512/skychb1629.png">UK: Film4+1</channel>
  <channel site="sky.com" lang="en" xmltv_id="FoodNetwork.uk" site_id="3590" logo="https://d2n0069hmnqmmx.cloudfront.net/epgdata/1.0/newchanlogos/512/512/skychb3590.png">UK: Food Network</channel>
  <channel site="sky.com" lang="en" xmltv_id="FoodNetworkPlus1.uk" site_id="3592" logo="https://d2n0069hmnqmmx.cloudfront.net/epgdata/1.0/newchanlogos/512/512/skychb3592.png">UK: Food Netwrk+1</channel>
  <channel site="sky.com" lang="en" xmltv_id="Foodxp.uk" site_id="1227" logo="https://d2n0069hmnqmmx.cloudfront.net/epgdata/1.0/newchanlogos/512/512/skychb1227.png">UK: Foodxp</channel>
  <channel site="sky.com" lang="en" xmltv_id="France24English.fr" site_id="1121" logo="https://d2n0069hmnqmmx.cloudfront.net/epgdata/1.0/newchanlogos/512/512/skychb1121.png">UK: FRANCE 24 HD</channel>
  <channel site="sky.com" lang="en" xmltv_id="GBNews.uk" site_id="1196" logo="https://d2n0069hmnqmmx.cloudfront.net/epgdata/1.0/newchanlogos/512/512/skychb1196.png">UK: GB News HD</channel>
  <channel site="sky.com" lang="en" xmltv_id="GemsTV.uk" site_id="3010" logo="https://d2n0069hmnqmmx.cloudfront.net/epgdata/1.0/newchanlogos/512/512/skychb3010.png">UK: Gems TV</channel>
  <channel site="sky.com" lang="en" xmltv_id="GeoNewsInternational.pk" site_id="4407" logo="https://d2n0069hmnqmmx.cloudfront.net/epgdata/1.0/newchanlogos/512/512/skychb4407.png">UK: GEO News</channel>
  <channel site="sky.com" lang="en" xmltv_id="GODTV.uk" site_id="3105" logo="https://d2n0069hmnqmmx.cloudfront.net/epgdata/1.0/newchanlogos/512/512/skychb3105.png">UK: GOD Channel</channel>
  <channel site="sky.com" lang="en" xmltv_id="GOLD.uk" site_id="2304" logo="https://d2n0069hmnqmmx.cloudfront.net/epgdata/1.0/newchanlogos/512/512/skychb2304.png">UK: GOLD</channel>
  <channel site="sky.com" lang="en" xmltv_id="GOLDHD.uk" site_id="6513" logo="https://d2n0069hmnqmmx.cloudfront.net/epgdata/1.0/newchanlogos/512/512/skychb6513.png">UK: GOLD HD</channel>
  <channel site="sky.com" lang="en" xmltv_id="GOLDPlus1.uk" site_id="2703" logo="https://d2n0069hmnqmmx.cloudfront.net/epgdata/1.0/newchanlogos/512/512/skychb2703.png">UK: GOLD+1</channel>
  <channel site="sky.com" lang="en" xmltv_id="GREATaction.uk" site_id="3708" logo="https://d2n0069hmnqmmx.cloudfront.net/epgdata/1.0/newchanlogos/512/512/skychb3708.png">UK: GREAT! action</channel>
  <channel site="sky.com" lang="en" xmltv_id="GREATactionPlus1.uk" site_id="3721" logo="https://d2n0069hmnqmmx.cloudfront.net/epgdata/1.0/newchanlogos/512/512/skychb3721.png">UK: GREAT!action+1</channel>
  <channel site="sky.com" lang="en" xmltv_id="GREATmovies.uk" site_id="3709" logo="https://d2n0069hmnqmmx.cloudfront.net/epgdata/1.0/newchanlogos/512/512/skychb3709.png">UK: GREAT! movies</channel>
  <channel site="sky.com" lang="en" xmltv_id="GREATmoviesPlus1.uk" site_id="3771" logo="https://d2n0069hmnqmmx.cloudfront.net/epgdata/1.0/newchanlogos/512/512/skychb3771.png">UK: GREAT! movies+1</channel>
  <channel site="sky.com" lang="en" xmltv_id="GREATromance.uk" site_id="3643" logo="https://d2n0069hmnqmmx.cloudfront.net/epgdata/1.0/newchanlogos/512/512/skychb3643.png">UK: GREAT! xmas</channel>
  <channel site="sky.com" lang="en" xmltv_id="GREATromancePlus1.uk" site_id="3751" logo="https://d2n0069hmnqmmx.cloudfront.net/epgdata/1.0/newchanlogos/512/512/skychb3751.png">UK: GREAT! xmas+1</channel>
  <channel site="sky.com" lang="en" xmltv_id="GREATtv.uk" site_id="4266" logo="https://d2n0069hmnqmmx.cloudfront.net/epgdata/1.0/newchanlogos/512/512/skychb4266.png">UK: GREAT! tv</channel>
  <channel site="sky.com" lang="en" xmltv_id="GREATtvPlus1.uk" site_id="5338" logo="https://d2n0069hmnqmmx.cloudfront.net/epgdata/1.0/newchanlogos/512/512/skychb5338.png">UK: GREAT! tv+1</channel>
  <channel site="sky.com" lang="en" xmltv_id="HGTV.uk" site_id="2301" logo="https://d2n0069hmnqmmx.cloudfront.net/epgdata/1.0/newchanlogos/512/512/skychb2301.png">UK: HGTV</channel>
  <channel site="sky.com" lang="en" xmltv_id="HGTVPlus1.uk" site_id="2309" logo="https://d2n0069hmnqmmx.cloudfront.net/epgdata/1.0/newchanlogos/512/512/skychb2309.png">UK: HGTV+1</channel>
  <channel site="sky.com" lang="en" xmltv_id="HidayatTV.uk" site_id="4549" logo="https://d2n0069hmnqmmx.cloudfront.net/epgdata/1.0/newchanlogos/512/512/skychb4549.png">UK: Hidayat TV</channel>
  <channel site="sky.com" lang="en" xmltv_id="HighStreetTV1.uk" site_id="3580" logo="https://d2n0069hmnqmmx.cloudfront.net/epgdata/1.0/newchanlogos/512/512/skychb3580.png">UK: High Street TV 1</channel>
  <channel site="sky.com" lang="en" xmltv_id="HighStreetTV2.uk" site_id="5706" logo="https://d2n0069hmnqmmx.cloudfront.net/epgdata/1.0/newchanlogos/512/512/skychb5706.png">UK: High Street TV 2</channel>
  <channel site="sky.com" lang="en" xmltv_id="HighStreetTV3.uk" site_id="3404" logo="https://d2n0069hmnqmmx.cloudfront.net/epgdata/1.0/newchanlogos/512/512/skychb3404.png">UK: High Street TV 3</channel>
  <channel site="sky.com" lang="en" xmltv_id="HighStreetTV4.uk" site_id="1130" logo="https://d2n0069hmnqmmx.cloudfront.net/epgdata/1.0/newchanlogos/512/512/skychb1130.png">UK: High Street TV 4</channel>
  <channel site="sky.com" lang="en" xmltv_id="HorrorXtra.uk" site_id="3605" logo="https://d2n0069hmnqmmx.cloudfront.net/epgdata/1.0/newchanlogos/512/512/skychb3605.png">UK: LEGEND XTRA</channel>
  <channel site="sky.com" lang="en" xmltv_id="HorrorXtraPlus1.uk" site_id="4502" logo="https://d2n0069hmnqmmx.cloudfront.net/epgdata/1.0/newchanlogos/512/512/skychb4502.png">UK: LEGEND XTRA+1</channel>
  <channel site="sky.com" lang="en" xmltv_id="IdealWorldTV.uk" site_id="5212" logo="https://d2n0069hmnqmmx.cloudfront.net/epgdata/1.0/newchanlogos/512/512/skychb5212.png">UK: Ideal World</channel>
  <channel site="sky.com" lang="en" xmltv_id="IndiaTodayInternational.in" site_id="1057" logo="https://d2n0069hmnqmmx.cloudfront.net/epgdata/1.0/newchanlogos/512/512/skychb1057.png">UK: India Today</channel>
  <channel site="sky.com" lang="en" xmltv_id="InspirationTV.us" site_id="3219" logo="https://d2n0069hmnqmmx.cloudfront.net/epgdata/1.0/newchanlogos/512/512/skychb3219.png">UK: Inspiration TV</channel>
  <channel site="sky.com" lang="en" xmltv_id="InvestigationDiscovery.uk" site_id="2413" logo="https://d2n0069hmnqmmx.cloudfront.net/epgdata/1.0/newchanlogos/512/512/skychb2413.png">UK: ID</channel>
  <channel site="sky.com" lang="en" xmltv_id="InvestigationDiscoveryPlus1.uk" site_id="5452" logo="https://d2n0069hmnqmmx.cloudfront.net/epgdata/1.0/newchanlogos/512/512/skychb5452.png">UK: ID+1</channel>
  <channel site="sky.com" lang="en" xmltv_id="IonTV.uk" site_id="4461" logo="https://d2n0069hmnqmmx.cloudfront.net/epgdata/1.0/newchanlogos/512/512/skychb4461.png">UK: iON TV</channel>
  <channel site="sky.com" lang="en" xmltv_id="IqraTV.uk" site_id="6754" logo="https://d2n0069hmnqmmx.cloudfront.net/epgdata/1.0/newchanlogos/512/512/skychb6754.png">UK: IQRA TV</channel>
  <channel site="sky.com" lang="en" xmltv_id="IslamChannel.uk" site_id="3214" logo="https://d2n0069hmnqmmx.cloudfront.net/epgdata/1.0/newchanlogos/512/512/skychb3214.png">UK: Islam Channel</channel>
  <channel site="sky.com" lang="en" xmltv_id="IslamTV.uk" site_id="4403" logo="https://d2n0069hmnqmmx.cloudfront.net/epgdata/1.0/newchanlogos/512/512/skychb4403.png">UK: Islam TV</channel>
  <channel site="sky.com" lang="en" xmltv_id="ITV1.uk" site_id="6000" logo="https://d2n0069hmnqmmx.cloudfront.net/epgdata/1.0/newchanlogos/512/512/skychb6000.png">UK: ITV1</channel>
  <channel site="sky.com" lang="en" xmltv_id="ITV1HD.uk" site_id="6504" logo="https://d2n0069hmnqmmx.cloudfront.net/epgdata/1.0/newchanlogos/512/512/skychb6504.png">UK: ITV1 HD</channel>
  <channel site="sky.com" lang="en" xmltv_id="ITV1Plus1.uk" site_id="6155" logo="https://d2n0069hmnqmmx.cloudfront.net/epgdata/1.0/newchanlogos/512/512/skychb6155.png">UK: ITV1+1</channel>
  <channel site="sky.com" lang="en" xmltv_id="ITV2.uk" site_id="6240" logo="https://d2n0069hmnqmmx.cloudfront.net/epgdata/1.0/newchanlogos/512/512/skychb6240.png">UK: ITV2</channel>
  <channel site="sky.com" lang="en" xmltv_id="ITV2HD.uk" site_id="6532" logo="https://d2n0069hmnqmmx.cloudfront.net/epgdata/1.0/newchanlogos/512/512/skychb6532.png">UK: ITV2 HD</channel>
  <channel site="sky.com" lang="en" xmltv_id="ITV2Plus1.uk" site_id="6241" logo="https://d2n0069hmnqmmx.cloudfront.net/epgdata/1.0/newchanlogos/512/512/skychb6241.png">UK: ITV2+1</channel>
  <channel site="sky.com" lang="en" xmltv_id="ITV3.uk" site_id="6260" logo="https://d2n0069hmnqmmx.cloudfront.net/epgdata/1.0/newchanlogos/512/512/skychb6260.png">UK: ITV3</channel>
  <channel site="sky.com" lang="en" xmltv_id="ITV3HD.uk" site_id="6533" logo="https://d2n0069hmnqmmx.cloudfront.net/epgdata/1.0/newchanlogos/512/512/skychb6533.png">UK: ITV3 HD</channel>
  <channel site="sky.com" lang="en" xmltv_id="ITV3Plus1.uk" site_id="6261" logo="https://d2n0069hmnqmmx.cloudfront.net/epgdata/1.0/newchanlogos/512/512/skychb6261.png">UK: ITV3+1</channel>
  <channel site="sky.com" lang="en" xmltv_id="ITV4.uk" site_id="6272" logo="https://d2n0069hmnqmmx.cloudfront.net/epgdata/1.0/newchanlogos/512/512/skychb6272.png">UK: ITV4</channel>
  <channel site="sky.com" lang="en" xmltv_id="ITV4HD.uk" site_id="6534" logo="https://d2n0069hmnqmmx.cloudfront.net/epgdata/1.0/newchanlogos/512/512/skychb6534.png">UK: ITV4 HD</channel>
  <channel site="sky.com" lang="en" xmltv_id="ITV4Plus1.uk" site_id="6274" logo="https://d2n0069hmnqmmx.cloudfront.net/epgdata/1.0/newchanlogos/512/512/skychb6274.png">UK: ITV4+1</channel>
  <channel site="sky.com" lang="en" xmltv_id="ITVBe.uk" site_id="6508" logo="https://d2n0069hmnqmmx.cloudfront.net/epgdata/1.0/newchanlogos/512/512/skychb6508.png">UK: ITVBe</channel>
  <channel site="sky.com" lang="en" xmltv_id="JewelleryMaker.uk" site_id="3354" logo="https://d2n0069hmnqmmx.cloudfront.net/epgdata/1.0/newchanlogos/512/512/skychb3354.png">UK: JewelleryMaker</channel>
  <channel site="sky.com" lang="en" xmltv_id="JMLDirectTV.uk" site_id="5761" logo="https://d2n0069hmnqmmx.cloudfront.net/epgdata/1.0/newchanlogos/512/512/skychb5761.png">UK: JML Direct</channel>
  <channel site="sky.com" lang="en" xmltv_id="KanshiTV.uk" site_id="3753" logo="https://d2n0069hmnqmmx.cloudfront.net/epgdata/1.0/newchanlogos/512/512/skychb3753.png">UK: Kanshi TV</channel>
  <channel site="sky.com" lang="en" xmltv_id="Kerrang.uk" site_id="1853" logo="https://d2n0069hmnqmmx.cloudfront.net/epgdata/1.0/newchanlogos/512/512/skychb1853.png">UK: Kerrang!</channel>
  <channel site="sky.com" lang="en" xmltv_id="KICCTV.uk" site_id="3776" logo="https://d2n0069hmnqmmx.cloudfront.net/epgdata/1.0/newchanlogos/512/512/skychb3776.png">UK: KICC TV</channel>
  <channel site="sky.com" lang="en" xmltv_id="KissTV.uk" site_id="1858" logo="https://d2n0069hmnqmmx.cloudfront.net/epgdata/1.0/newchanlogos/512/512/skychb1858.png">UK: KISS</channel>
  <channel site="sky.com" lang="en" xmltv_id="Legend.uk" site_id="4610" logo="https://d2n0069hmnqmmx.cloudfront.net/epgdata/1.0/newchanlogos/512/512/skychb4610.png">UK: LEGEND</channel>
  <channel site="sky.com" lang="en" xmltv_id="LFCTV.uk" site_id="3845" logo="https://d2n0069hmnqmmx.cloudfront.net/epgdata/1.0/newchanlogos/512/512/skychb3845.png">UK: LFCTV HD</channel>
  <channel site="sky.com" lang="en" xmltv_id="LondonLive.uk" site_id="5090" logo="https://d2n0069hmnqmmx.cloudfront.net/epgdata/1.0/newchanlogos/512/512/skychb5090.png">UK: London Live</channel>
  <channel site="sky.com" lang="en" xmltv_id="LoveWorldUK.uk" site_id="1228" logo="https://d2n0069hmnqmmx.cloudfront.net/epgdata/1.0/newchanlogos/512/512/skychb1228.png">UK: LoveWorld HD</channel>
  <channel site="sky.com" lang="en" xmltv_id="MadaniChannelEnglish.pk" site_id="4460" logo="https://d2n0069hmnqmmx.cloudfront.net/epgdata/1.0/newchanlogos/512/512/skychb4460.png">UK: Madani Chnl</channel>
  <channel site="sky.com" lang="en" xmltv_id="Magic.uk" site_id="1877" logo="https://d2n0069hmnqmmx.cloudfront.net/epgdata/1.0/newchanlogos/512/512/skychb1877.png">UK: Magic</channel>
  <channel site="sky.com" lang="en" xmltv_id="More4.uk" site_id="3340" logo="https://d2n0069hmnqmmx.cloudfront.net/epgdata/1.0/newchanlogos/512/512/skychb3340.png">UK: More4</channel>
  <channel site="sky.com" lang="en" xmltv_id="More4HD.uk" site_id="4043" logo="https://d2n0069hmnqmmx.cloudfront.net/epgdata/1.0/newchanlogos/512/512/skychb4043.png">UK: More4 HD</channel>
  <channel site="sky.com" lang="en" xmltv_id="More4Plus1.uk" site_id="3310" logo="https://d2n0069hmnqmmx.cloudfront.net/epgdata/1.0/newchanlogos/512/512/skychb3310.png">UK: More4+1</channel>
  <channel site="sky.com" lang="en" xmltv_id="Movies24.uk" site_id="4420" logo="https://d2n0069hmnqmmx.cloudfront.net/epgdata/1.0/newchanlogos/512/512/skychb4420.png">UK: Christmas24</channel>
  <channel site="sky.com" lang="en" xmltv_id="Movies24Plus.uk" site_id="4421" logo="https://d2n0069hmnqmmx.cloudfront.net/epgdata/1.0/newchanlogos/512/512/skychb4421.png">UK: Christmas24+</channel>
  <channel site="sky.com" lang="en" xmltv_id="MTV.uk" site_id="2501" logo="https://d2n0069hmnqmmx.cloudfront.net/epgdata/1.0/newchanlogos/512/512/skychb2501.png">UK: MTV</channel>
  <channel site="sky.com" lang="en" xmltv_id="MTVBase.uk" site_id="2508" logo="https://d2n0069hmnqmmx.cloudfront.net/epgdata/1.0/newchanlogos/512/512/skychb2508.png">UK: MTV XMAS</channel>
  <channel site="sky.com" lang="en" xmltv_id="MTVClassic.uk" site_id="2509" logo="https://d2n0069hmnqmmx.cloudfront.net/epgdata/1.0/newchanlogos/512/512/skychb2509.png">UK: MTV 80s</channel>
  <channel site="sky.com" lang="en" xmltv_id="MTVHD.uk" site_id="3831" logo="https://d2n0069hmnqmmx.cloudfront.net/epgdata/1.0/newchanlogos/512/512/skychb3831.png">UK: MTV HD</channel>
  <channel site="sky.com" lang="en" xmltv_id="MTVHits.uk" site_id="2506" logo="https://d2n0069hmnqmmx.cloudfront.net/epgdata/1.0/newchanlogos/512/512/skychb2506.png">UK: MTV HITS</channel>
  <channel site="sky.com" lang="en" xmltv_id="MTVMusic.uk" site_id="2512" logo="https://d2n0069hmnqmmx.cloudfront.net/epgdata/1.0/newchanlogos/512/512/skychb2512.png">UK: MTV MUSIC</channel>
  <channel site="sky.com" lang="en" xmltv_id="MUTV.uk" site_id="1003" logo="https://d2n0069hmnqmmx.cloudfront.net/epgdata/1.0/newchanlogos/512/512/skychb1003.png">UK: MUTV HD</channel>
  <channel site="sky.com" lang="en" xmltv_id="MUTV.uk" site_id="1834" logo="https://d2n0069hmnqmmx.cloudfront.net/epgdata/1.0/newchanlogos/512/512/skychb1834.png">UK: MUTV</channel>
  <channel site="sky.com" lang="en" xmltv_id="NationalGeographic.uk" site_id="1806" logo="https://d2n0069hmnqmmx.cloudfront.net/epgdata/1.0/newchanlogos/512/512/skychb1806.png">UK: Nat Geo</channel>
  <channel site="sky.com" lang="en" xmltv_id="NationalGeographic.uk" site_id="4031" logo="https://d2n0069hmnqmmx.cloudfront.net/epgdata/1.0/newchanlogos/512/512/skychb4031.png">UK: Nat Geo HD</channel>
  <channel site="sky.com" lang="en" xmltv_id="NationalGeographicPlus1.uk" site_id="1822" logo="https://d2n0069hmnqmmx.cloudfront.net/epgdata/1.0/newchanlogos/512/512/skychb1822.png">UK: Nat Geo+1</channel>
  <channel site="sky.com" lang="en" xmltv_id="NationalGeographicWild.uk" site_id="1847" logo="https://d2n0069hmnqmmx.cloudfront.net/epgdata/1.0/newchanlogos/512/512/skychb1847.png">UK: Nat Geo Wild</channel>
  <channel site="sky.com" lang="en" xmltv_id="NationalGeographicWild.uk" site_id="4025" logo="https://d2n0069hmnqmmx.cloudfront.net/epgdata/1.0/newchanlogos/512/512/skychb4025.png">UK: NatGeoWild HD</channel>
  <channel site="sky.com" lang="en" xmltv_id="NBCNewsNOW.us" site_id="1039" logo="https://d2n0069hmnqmmx.cloudfront.net/epgdata/1.0/newchanlogos/512/512/skychb1039.png">UK: NBCNewsNowHD</channel>
  <channel site="sky.com" lang="en" xmltv_id="NDTV24x7.in" site_id="1821" logo="https://d2n0069hmnqmmx.cloudfront.net/epgdata/1.0/newchanlogos/512/512/skychb1821.png">UK: NDTV 24x7</channel>
  <channel site="sky.com" lang="en" xmltv_id="NewMediaHD.uk" site_id="1131" logo="https://d2n0069hmnqmmx.cloudfront.net/epgdata/1.0/newchanlogos/512/512/skychb1131.png">UK: New Media HD</channel>
  <channel site="sky.com" lang="en" xmltv_id="NewVision.uk" site_id="1026" logo="https://d2n0069hmnqmmx.cloudfront.net/epgdata/1.0/newchanlogos/512/512/skychb1026.png">UK: New Vision TV</channel>
  <channel site="sky.com" lang="en" xmltv_id="NHKWorldJapan.jp" site_id="3147" logo="https://d2n0069hmnqmmx.cloudfront.net/epgdata/1.0/newchanlogos/512/512/skychb3147.png">UK: NHK World HD</channel>
  <channel site="sky.com" lang="en" xmltv_id="Nickelodeon.uk" site_id="1846" logo="https://d2n0069hmnqmmx.cloudfront.net/epgdata/1.0/newchanlogos/512/512/skychb1846.png">UK: Nickelodeon</channel>
  <channel site="sky.com" lang="en" xmltv_id="NickelodeonHD.uk" site_id="4069" logo="https://d2n0069hmnqmmx.cloudfront.net/epgdata/1.0/newchanlogos/512/512/skychb4069.png">UK: NickelodeonHD</channel>
  <channel site="sky.com" lang="en" xmltv_id="NickelodeonPlus1.uk" site_id="1845" logo="https://d2n0069hmnqmmx.cloudfront.net/epgdata/1.0/newchanlogos/512/512/skychb1845.png">UK: Nickelodeon+1</channel>
  <channel site="sky.com" lang="en" xmltv_id="NickJr.uk" site_id="1857" logo="https://d2n0069hmnqmmx.cloudfront.net/epgdata/1.0/newchanlogos/512/512/skychb1857.png">UK: Nick Jr.</channel>
  <channel site="sky.com" lang="en" xmltv_id="NickJr.uk" site_id="4039" logo="https://d2n0069hmnqmmx.cloudfront.net/epgdata/1.0/newchanlogos/512/512/skychb4039.png">UK: Nick Jr. HD</channel>
  <channel site="sky.com" lang="en" xmltv_id="NickJrPlus1.uk" site_id="5089" logo="https://d2n0069hmnqmmx.cloudfront.net/epgdata/1.0/newchanlogos/512/512/skychb5089.png">UK: Nick Jr+1</channel>
  <channel site="sky.com" lang="en" xmltv_id="NickJrToo.uk" site_id="4340" logo="https://d2n0069hmnqmmx.cloudfront.net/epgdata/1.0/newchanlogos/512/512/skychb4340.png">UK: NickJrPAWPatrol</channel>
  <channel site="sky.com" lang="en" xmltv_id="Nicktoons.uk" site_id="1849" logo="https://d2n0069hmnqmmx.cloudfront.net/epgdata/1.0/newchanlogos/512/512/skychb1849.png">UK: NickSpongeBob</channel>
  <channel site="sky.com" lang="en" xmltv_id="NoorTV.uk" site_id="3715" logo="https://d2n0069hmnqmmx.cloudfront.net/epgdata/1.0/newchanlogos/512/512/skychb3715.png">UK: Noor TV</channel>
  <channel site="sky.com" lang="en" xmltv_id="Now70s.uk" site_id="3403" logo="https://d2n0069hmnqmmx.cloudfront.net/epgdata/1.0/newchanlogos/512/512/skychb3403.png">UK: NOW 70s</channel>
  <channel site="sky.com" lang="en" xmltv_id="Now80s.uk" site_id="4541" logo="https://d2n0069hmnqmmx.cloudfront.net/epgdata/1.0/newchanlogos/512/512/skychb4541.png">UK: NOW 80s</channel>
  <channel site="sky.com" lang="en" xmltv_id="NOWRock.uk" site_id="3682" logo="https://d2n0069hmnqmmx.cloudfront.net/epgdata/1.0/newchanlogos/512/512/skychb3682.png">UK: NOW ROCK</channel>
  <channel site="sky.com" lang="en" xmltv_id="PBSAmerica.uk" site_id="5500" logo="https://d2n0069hmnqmmx.cloudfront.net/epgdata/1.0/newchanlogos/512/512/skychb5500.png">UK: PBS America</channel>
  <channel site="sky.com" lang="en" xmltv_id="PhoenixCNEChannelHD.hk" site_id="1140" logo="https://d2n0069hmnqmmx.cloudfront.net/epgdata/1.0/newchanlogos/512/512/skychb1140.png">UK: PCNE Chinese HD</channel>
  <channel site="sky.com" lang="en" xmltv_id="Pitaara.in" site_id="1260" logo="https://d2n0069hmnqmmx.cloudfront.net/epgdata/1.0/newchanlogos/512/512/skychb1260.png">UK: Pitaara</channel>
  <channel site="sky.com" lang="en" xmltv_id="PoliticsPunjab.uk" site_id="3421" logo="https://d2n0069hmnqmmx.cloudfront.net/epgdata/1.0/newchanlogos/512/512/skychb3421.png">UK: PoliticsPunjab</channel>
  <channel site="sky.com" lang="en" xmltv_id="Pop.uk" site_id="3750" logo="https://d2n0069hmnqmmx.cloudfront.net/epgdata/1.0/newchanlogos/512/512/skychb3750.png">UK: POP</channel>
  <channel site="sky.com" lang="en" xmltv_id="PopMax.uk" site_id="4262" logo="https://d2n0069hmnqmmx.cloudfront.net/epgdata/1.0/newchanlogos/512/512/skychb4262.png">UK: POP Max</channel>
  <channel site="sky.com" lang="en" xmltv_id="PopMaxPlus1.uk" site_id="4263" logo="https://d2n0069hmnqmmx.cloudfront.net/epgdata/1.0/newchanlogos/512/512/skychb4263.png">UK: POP Max+1</channel>
  <channel site="sky.com" lang="en" xmltv_id="PopPlus1.uk" site_id="4216" logo="https://d2n0069hmnqmmx.cloudfront.net/epgdata/1.0/newchanlogos/512/512/skychb4216.png">UK: POP+1</channel>
  <channel site="sky.com" lang="en" xmltv_id="PTCPunjabi.in" site_id="5715" logo="https://d2n0069hmnqmmx.cloudfront.net/epgdata/1.0/newchanlogos/512/512/skychb5715.png">UK: PTC PUNJABI</channel>
  <channel site="sky.com" lang="en" xmltv_id="PTVGlobal.pk" site_id="3646" logo="https://d2n0069hmnqmmx.cloudfront.net/epgdata/1.0/newchanlogos/512/512/skychb3646.png">UK: PTV Global</channel>
  <channel site="sky.com" lang="en" xmltv_id="Quest.uk" site_id="1128" logo="https://d2n0069hmnqmmx.cloudfront.net/epgdata/1.0/newchanlogos/512/512/skychb1128.png">UK: QUEST HD</channel>
  <channel site="sky.com" lang="en" xmltv_id="Quest.uk" site_id="6761" logo="https://d2n0069hmnqmmx.cloudfront.net/epgdata/1.0/newchanlogos/512/512/skychb6761.png">UK: QUEST</channel>
  <channel site="sky.com" lang="en" xmltv_id="QuestPlus1.uk" site_id="3621" logo="https://d2n0069hmnqmmx.cloudfront.net/epgdata/1.0/newchanlogos/512/512/skychb3621.png">UK: QUEST+1</channel>
  <channel site="sky.com" lang="en" xmltv_id="QuestRed.uk" site_id="2411" logo="https://d2n0069hmnqmmx.cloudfront.net/epgdata/1.0/newchanlogos/512/512/skychb2411.png">UK: Quest Red</channel>
  <channel site="sky.com" lang="en" xmltv_id="QuestRedPlus1.uk" site_id="4547" logo="https://d2n0069hmnqmmx.cloudfront.net/epgdata/1.0/newchanlogos/512/512/skychb4547.png">UK: Quest Red+1</channel>
  <channel site="sky.com" lang="en" xmltv_id="QVCBeauty.uk" site_id="4105" logo="https://d2n0069hmnqmmx.cloudfront.net/epgdata/1.0/newchanlogos/512/512/skychb4105.png">UK: QVC Beauty</channel>
  <channel site="sky.com" lang="en" xmltv_id="QVCExtra.uk" site_id="3359" logo="https://d2n0069hmnqmmx.cloudfront.net/epgdata/1.0/newchanlogos/512/512/skychb3359.png">UK: QVC Extra</channel>
  <channel site="sky.com" lang="en" xmltv_id="QVCHD.uk" site_id="1076" logo="https://d2n0069hmnqmmx.cloudfront.net/epgdata/1.0/newchanlogos/512/512/skychb1076.png">UK: QVC HD</channel>
  <channel site="sky.com" lang="en" xmltv_id="QVCStyleHD.uk" site_id="1118" logo="https://d2n0069hmnqmmx.cloudfront.net/epgdata/1.0/newchanlogos/512/512/skychb1118.png">UK: QVC Style HD</channel>
  <channel site="sky.com" lang="en" xmltv_id="RacingTV.uk" site_id="3636" logo="https://d2n0069hmnqmmx.cloudfront.net/epgdata/1.0/newchanlogos/512/512/skychb3636.png">UK: Racing TV</channel>
  <channel site="sky.com" lang="en" xmltv_id="RacingTVHD.uk" site_id="5272" logo="https://d2n0069hmnqmmx.cloudfront.net/epgdata/1.0/newchanlogos/512/512/skychb5272.png">UK: Racing TV HD</channel>
  <channel site="sky.com" lang="en" xmltv_id="RealityXtra.uk" site_id="3617" logo="https://d2n0069hmnqmmx.cloudfront.net/epgdata/1.0/newchanlogos/512/512/skychb3617.png">UK: TRUE CRIME X</channel>
  <channel site="sky.com" lang="en" xmltv_id="Really.uk" site_id="2325" logo="https://d2n0069hmnqmmx.cloudfront.net/epgdata/1.0/newchanlogos/512/512/skychb2325.png">UK: Really</channel>
  <channel site="sky.com" lang="en" xmltv_id="RevelationTV.uk" site_id="3116" logo="https://d2n0069hmnqmmx.cloudfront.net/epgdata/1.0/newchanlogos/512/512/skychb3116.png">UK: revelation</channel>
  <channel site="sky.com" lang="en" xmltv_id="S4C.uk" site_id="5701" logo="https://d2n0069hmnqmmx.cloudfront.net/epgdata/1.0/newchanlogos/512/512/skychb5701.png">UK: S4C</channel>
  <channel site="sky.com" lang="en" xmltv_id="S4CHD.uk" site_id="2296" logo="https://d2n0069hmnqmmx.cloudfront.net/epgdata/1.0/newchanlogos/512/512/skychb2296.png">UK: S4C HD</channel>
  <channel site="sky.com" lang="en" xmltv_id="SamaaTV.pk" site_id="1145" logo="https://d2n0069hmnqmmx.cloudfront.net/epgdata/1.0/newchanlogos/512/512/skychb1145.png">UK: Samaa TV</channel>
  <channel site="sky.com" lang="en" xmltv_id="SangatTV.uk" site_id="3355" logo="https://d2n0069hmnqmmx.cloudfront.net/epgdata/1.0/newchanlogos/512/512/skychb3355.png">UK: Sangat</channel>
  <channel site="sky.com" lang="en" xmltv_id="SikhChannel.uk" site_id="3650" logo="https://d2n0069hmnqmmx.cloudfront.net/epgdata/1.0/newchanlogos/512/512/skychb3650.png">UK: Sikh Channel</channel>
  <channel site="sky.com" lang="en" xmltv_id="SkyArts.uk" site_id="1752" logo="https://d2n0069hmnqmmx.cloudfront.net/epgdata/1.0/newchanlogos/512/512/skychb1752.png">UK: Sky Arts</channel>
  <channel site="sky.com" lang="en" xmltv_id="SkyArtsHD.uk" site_id="4063" logo="https://d2n0069hmnqmmx.cloudfront.net/epgdata/1.0/newchanlogos/512/512/skychb4063.png">UK: Sky Arts HD</channel>
  <channel site="sky.com" lang="en" xmltv_id="SkyAtlantic.uk" site_id="1412" logo="https://d2n0069hmnqmmx.cloudfront.net/epgdata/1.0/newchanlogos/512/512/skychb1412.png">UK: Sky Atlantic</channel>
  <channel site="sky.com" lang="en" xmltv_id="SkyAtlanticHD.uk" site_id="4053" logo="https://d2n0069hmnqmmx.cloudfront.net/epgdata/1.0/newchanlogos/512/512/skychb4053.png">UK: Sky Atlantic HD</channel>
  <channel site="sky.com" lang="en" xmltv_id="SkyAtlanticPlus1.uk" site_id="1413" logo="https://d2n0069hmnqmmx.cloudfront.net/epgdata/1.0/newchanlogos/512/512/skychb1413.png">UK: Sky Atlantic+1</channel>
  <channel site="sky.com" lang="en" xmltv_id="SkyCinemaAction.uk" site_id="1001" logo="https://d2n0069hmnqmmx.cloudfront.net/epgdata/1.0/newchanlogos/512/512/skychb1001.png">UK: Sky Action</channel>
  <channel site="sky.com" lang="en" xmltv_id="SkyCinemaActionHD.uk" site_id="4014" logo="https://d2n0069hmnqmmx.cloudfront.net/epgdata/1.0/newchanlogos/512/512/skychb4014.png">UK: Sky Action HD</channel>
  <channel site="sky.com" lang="en" xmltv_id="SkyCinemaAnimation.uk" site_id="1199" logo="https://d2n0069hmnqmmx.cloudfront.net/epgdata/1.0/newchanlogos/512/512/skychb1199.png">UK: SkyAnimationHD</channel>
  <channel site="sky.com" lang="en" xmltv_id="SkyCinemaComedyHD.uk" site_id="4019" logo="https://d2n0069hmnqmmx.cloudfront.net/epgdata/1.0/newchanlogos/512/512/skychb4019.png">UK: Sky Comedy HD</channel>
  <channel site="sky.com" lang="en" xmltv_id="SkyCinemaDramaHD.uk" site_id="4016" logo="https://d2n0069hmnqmmx.cloudfront.net/epgdata/1.0/newchanlogos/512/512/skychb4016.png">UK: SkyChristmasHD</channel>
  <channel site="sky.com" lang="en" xmltv_id="SkyCinemaFamily.uk" site_id="1808" logo="https://d2n0069hmnqmmx.cloudfront.net/epgdata/1.0/newchanlogos/512/512/skychb1808.png">UK: Sky Family</channel>
  <channel site="sky.com" lang="en" xmltv_id="SkyCinemaFamilyHD.uk" site_id="4018" logo="https://d2n0069hmnqmmx.cloudfront.net/epgdata/1.0/newchanlogos/512/512/skychb4018.png">UK: Sky Family HD</channel>
  <channel site="sky.com" lang="en" xmltv_id="SkyCinemaGreats.uk" site_id="1815" logo="https://d2n0069hmnqmmx.cloudfront.net/epgdata/1.0/newchanlogos/512/512/skychb1815.png">UK: Sky 80s Icons</channel>
  <channel site="sky.com" lang="en" xmltv_id="SkyCinemaGreatsHD.uk" site_id="4015" logo="https://d2n0069hmnqmmx.cloudfront.net/epgdata/1.0/newchanlogos/512/512/skychb4015.png">UK: 80s Icons HD</channel>
  <channel site="sky.com" lang="en" xmltv_id="SkyCinemaHits.uk" site_id="4033" logo="https://d2n0069hmnqmmx.cloudfront.net/epgdata/1.0/newchanlogos/512/512/skychb4033.png">UK: Sky Hits HD</channel>
  <channel site="sky.com" lang="en" xmltv_id="SkyCinemaPremiere.uk" site_id="1409" logo="https://d2n0069hmnqmmx.cloudfront.net/epgdata/1.0/newchanlogos/512/512/skychb1409.png">UK: Sky Premiere</channel>
  <channel site="sky.com" lang="en" xmltv_id="SkyCinemaPremiereHD.uk" site_id="4021" logo="https://d2n0069hmnqmmx.cloudfront.net/epgdata/1.0/newchanlogos/512/512/skychb4021.png">UK: SkyPremiereHD</channel>
  <channel site="sky.com" lang="en" xmltv_id="SkyCinemaPremierePlus1.uk" site_id="1823" logo="https://d2n0069hmnqmmx.cloudfront.net/epgdata/1.0/newchanlogos/512/512/skychb1823.png">UK: SkyPremiere+1</channel>
  <channel site="sky.com" lang="en" xmltv_id="SkyCinemaSciFiHorrorHD.uk" site_id="4017" logo="https://d2n0069hmnqmmx.cloudfront.net/epgdata/1.0/newchanlogos/512/512/skychb4017.png">UK: Sky ScFi/HorHD</channel>
  <channel site="sky.com" lang="en" xmltv_id="SkyCinemaSelect.uk" site_id="4020" logo="https://d2n0069hmnqmmx.cloudfront.net/epgdata/1.0/newchanlogos/512/512/skychb4020.png">UK: SkyBestOf23HD</channel>
  <channel site="sky.com" lang="en" xmltv_id="SkyCinemaThrillerHD.uk" site_id="4062" logo="https://d2n0069hmnqmmx.cloudfront.net/epgdata/1.0/newchanlogos/512/512/skychb4062.png">UK: Sky Thriller HD</channel>
  <channel site="sky.com" lang="en" xmltv_id="SkyComedy.uk" site_id="1177" logo="https://d2n0069hmnqmmx.cloudfront.net/epgdata/1.0/newchanlogos/512/512/skychb1177.png">UK: Sky Comedy</channel>
  <channel site="sky.com" lang="en" xmltv_id="SkyComedyHD.uk" site_id="1143" logo="https://d2n0069hmnqmmx.cloudfront.net/epgdata/1.0/newchanlogos/512/512/skychb1143.png">UK: Sky Comedy HD</channel>
  <channel site="sky.com" lang="en" xmltv_id="SkyCrime.uk" site_id="2207" logo="https://d2n0069hmnqmmx.cloudfront.net/epgdata/1.0/newchanlogos/512/512/skychb2207.png">UK: Sky Crime</channel>
  <channel site="sky.com" lang="en" xmltv_id="SkyCrimeHD.uk" site_id="1212" logo="https://d2n0069hmnqmmx.cloudfront.net/epgdata/1.0/newchanlogos/512/512/skychb1212.png">UK: Sky Crime HD</channel>
  <channel site="sky.com" lang="en" xmltv_id="SkyCrimePlus1.uk" site_id="4330" logo="https://d2n0069hmnqmmx.cloudfront.net/epgdata/1.0/newchanlogos/512/512/skychb4330.png">UK: Sky Crime+1</channel>
  <channel site="sky.com" lang="en" xmltv_id="SkyDocumentaries.uk" site_id="1127" logo="https://d2n0069hmnqmmx.cloudfront.net/epgdata/1.0/newchanlogos/512/512/skychb1127.png">UK: SkyDocumntrs</channel>
  <channel site="sky.com" lang="en" xmltv_id="SkyDocumentariesHD.uk" site_id="1136" logo="https://d2n0069hmnqmmx.cloudfront.net/epgdata/1.0/newchanlogos/512/512/skychb1136.png">UK: SkyDocmntrsHD</channel>
  <channel site="sky.com" lang="en" xmltv_id="SkyHistory.uk" site_id="1875" logo="https://d2n0069hmnqmmx.cloudfront.net/epgdata/1.0/newchanlogos/512/512/skychb1875.png">UK: Sky History</channel>
  <channel site="sky.com" lang="en" xmltv_id="SkyHistory2.uk" site_id="1879" logo="https://d2n0069hmnqmmx.cloudfront.net/epgdata/1.0/newchanlogos/512/512/skychb1879.png">UK: Sky History2</channel>
  <channel site="sky.com" lang="en" xmltv_id="SkyHistory2HD.uk" site_id="1195" logo="https://d2n0069hmnqmmx.cloudfront.net/epgdata/1.0/newchanlogos/512/512/skychb1195.png">UK: SkyHistory2HD</channel>
  <channel site="sky.com" lang="en" xmltv_id="SkyHistoryHD.uk" site_id="4086" logo="https://d2n0069hmnqmmx.cloudfront.net/epgdata/1.0/newchanlogos/512/512/skychb4086.png">UK: Sky HistoryHD</channel>
  <channel site="sky.com" lang="en" xmltv_id="SkyHistoryPlus1.uk" site_id="1891" logo="https://d2n0069hmnqmmx.cloudfront.net/epgdata/1.0/newchanlogos/512/512/skychb1891.png">UK: Sky History+1</channel>
  <channel site="sky.com" lang="en" xmltv_id="SkyKidsHD.uk" site_id="1147" logo="https://d2n0069hmnqmmx.cloudfront.net/epgdata/1.0/newchanlogos/512/512/skychb1147.png">UK: Sky Kids HD</channel>
  <channel site="sky.com" lang="en" xmltv_id="SkyMax.uk" site_id="1402" logo="https://d2n0069hmnqmmx.cloudfront.net/epgdata/1.0/newchanlogos/512/512/skychb1402.png">UK: Sky Max</channel>
  <channel site="sky.com" lang="en" xmltv_id="SkyMaxHD.uk" site_id="4061" logo="https://d2n0069hmnqmmx.cloudfront.net/epgdata/1.0/newchanlogos/512/512/skychb4061.png">UK: Sky Max HD</channel>
  <channel site="sky.com" lang="en" xmltv_id="SkyMixHD.uk" site_id="1831" logo="https://d2n0069hmnqmmx.cloudfront.net/epgdata/1.0/newchanlogos/512/512/skychb1831.png">UK: Sky Mix HD</channel>
  <channel site="sky.com" lang="en" xmltv_id="SkyNature.uk" site_id="1165" logo="https://d2n0069hmnqmmx.cloudfront.net/epgdata/1.0/newchanlogos/512/512/skychb1165.png">UK: Sky Nature HD</channel>
  <channel site="sky.com" lang="en" xmltv_id="SkyNature.uk" site_id="1194" logo="https://d2n0069hmnqmmx.cloudfront.net/epgdata/1.0/newchanlogos/512/512/skychb1194.png">UK: Sky Nature</channel>
  <channel site="sky.com" lang="en" xmltv_id="SkyNews.uk" site_id="1404" logo="https://d2n0069hmnqmmx.cloudfront.net/epgdata/1.0/newchanlogos/512/512/skychb1404.png">UK: Sky News</channel>
  <channel site="sky.com" lang="en" xmltv_id="SkyNewsArabia.ae" site_id="4645" logo="https://d2n0069hmnqmmx.cloudfront.net/epgdata/1.0/newchanlogos/512/512/skychb4645.png">UK: SkyNewsArabia</channel>
  <channel site="sky.com" lang="en" xmltv_id="SkyNewsHD.uk" site_id="4050" logo="https://d2n0069hmnqmmx.cloudfront.net/epgdata/1.0/newchanlogos/512/512/skychb4050.png">UK: Sky News HD</channel>
  <channel site="sky.com" lang="en" xmltv_id="SkyReplay.uk" site_id="1833" logo="https://d2n0069hmnqmmx.cloudfront.net/epgdata/1.0/newchanlogos/512/512/skychb1833.png">UK: Sky Replay</channel>
  <channel site="sky.com" lang="en" xmltv_id="SkySciFi.uk" site_id="2505" logo="https://d2n0069hmnqmmx.cloudfront.net/epgdata/1.0/newchanlogos/512/512/skychb2505.png">UK: Sky Sci-Fi</channel>
  <channel site="sky.com" lang="en" xmltv_id="SkySciFi.uk" site_id="4074" logo="https://d2n0069hmnqmmx.cloudfront.net/epgdata/1.0/newchanlogos/512/512/skychb4074.png">UK: Sky Sci-Fi HD</channel>
  <channel site="sky.com" lang="en" xmltv_id="SkyShowcase.uk" site_id="1276" logo="https://d2n0069hmnqmmx.cloudfront.net/epgdata/1.0/newchanlogos/512/512/skychb1276.png">UK: Sky Showcase</channel>
  <channel site="sky.com" lang="en" xmltv_id="SkyShowcaseHD.uk" site_id="1275" logo="https://d2n0069hmnqmmx.cloudfront.net/epgdata/1.0/newchanlogos/512/512/skychb1275.png">UK: SkyShowcaseHD</channel>
  <channel site="sky.com" lang="en" xmltv_id="SkyShowcasePlus1.uk" site_id="1277" logo="https://d2n0069hmnqmmx.cloudfront.net/epgdata/1.0/newchanlogos/512/512/skychb1277.png">UK: SkyShowcase+1</channel>
  <channel site="sky.com" lang="en" xmltv_id="SkySportsArena.uk" site_id="3839" logo="https://d2n0069hmnqmmx.cloudfront.net/epgdata/1.0/newchanlogos/512/512/skychb3839.png">UK: SkySp Arena</channel>
  <channel site="sky.com" lang="en" xmltv_id="SkySportsArenaHD.uk" site_id="3940" logo="https://d2n0069hmnqmmx.cloudfront.net/epgdata/1.0/newchanlogos/512/512/skychb3940.png">UK: SkySp ArenaHD</channel>
  <channel site="sky.com" lang="en" xmltv_id="SkySportsBoxOffice.uk" site_id="1034" logo="https://d2n0069hmnqmmx.cloudfront.net/epgdata/1.0/newchanlogos/512/512/skychb1034.png">UK: SkySpBoxOff</channel>
  <channel site="sky.com" lang="en" xmltv_id="SkySportsCricket.uk" site_id="1302" logo="https://d2n0069hmnqmmx.cloudfront.net/epgdata/1.0/newchanlogos/512/512/skychb1302.png">UK: SkySp Cricket</channel>
  <channel site="sky.com" lang="en" xmltv_id="SkySportsCricketHD.uk" site_id="4081" logo="https://d2n0069hmnqmmx.cloudfront.net/epgdata/1.0/newchanlogos/512/512/skychb4081.png">UK: SkySpCricket HD</channel>
  <channel site="sky.com" lang="en" xmltv_id="SkySportsF1.uk" site_id="1306" logo="https://d2n0069hmnqmmx.cloudfront.net/epgdata/1.0/newchanlogos/512/512/skychb1306.png">UK: SkySp F1</channel>
  <channel site="sky.com" lang="en" xmltv_id="SkySportsF1HD.uk" site_id="3835" logo="https://d2n0069hmnqmmx.cloudfront.net/epgdata/1.0/newchanlogos/512/512/skychb3835.png">UK: SkySp F1 HD</channel>
  <channel site="sky.com" lang="en" xmltv_id="SkySportsFootball.uk" site_id="3838" logo="https://d2n0069hmnqmmx.cloudfront.net/epgdata/1.0/newchanlogos/512/512/skychb3838.png">UK: SkySp F'ball</channel>
  <channel site="sky.com" lang="en" xmltv_id="SkySportsFootballHD.uk" site_id="3939" logo="https://d2n0069hmnqmmx.cloudfront.net/epgdata/1.0/newchanlogos/512/512/skychb3939.png">UK: SkySp F'ball HD</channel>
  <channel site="sky.com" lang="en" xmltv_id="SkySportsGolf.uk" site_id="1322" logo="https://d2n0069hmnqmmx.cloudfront.net/epgdata/1.0/newchanlogos/512/512/skychb1322.png">UK: SkySp Golf</channel>
  <channel site="sky.com" lang="en" xmltv_id="SkySportsGolfHD.uk" site_id="4026" logo="https://d2n0069hmnqmmx.cloudfront.net/epgdata/1.0/newchanlogos/512/512/skychb4026.png">UK: SkySp Golf HD</channel>
  <channel site="sky.com" lang="en" xmltv_id="SkySportsMainEvent.uk" site_id="1301" logo="https://d2n0069hmnqmmx.cloudfront.net/epgdata/1.0/newchanlogos/512/512/skychb1301.png">UK: SkySpMainEv</channel>
  <channel site="sky.com" lang="en" xmltv_id="SkySportsMainEventHD.uk" site_id="4002" logo="https://d2n0069hmnqmmx.cloudfront.net/epgdata/1.0/newchanlogos/512/512/skychb4002.png">UK: SkySpMainEvHD</channel>
  <channel site="sky.com" lang="en" xmltv_id="SkySportsMix.uk" site_id="4090" logo="https://d2n0069hmnqmmx.cloudfront.net/epgdata/1.0/newchanlogos/512/512/skychb4090.png">UK: SkySp Mix HD</channel>
  <channel site="sky.com" lang="en" xmltv_id="SkySportsMix.uk" site_id="4091" logo="https://d2n0069hmnqmmx.cloudfront.net/epgdata/1.0/newchanlogos/512/512/skychb4091.png">UK: SkySp Mix</channel>
  <channel site="sky.com" lang="en" xmltv_id="SkySportsNews.uk" site_id="1314" logo="https://d2n0069hmnqmmx.cloudfront.net/epgdata/1.0/newchanlogos/512/512/skychb1314.png">UK: SkySp News</channel>
  <channel site="sky.com" lang="en" xmltv_id="SkySportsNewsHD.uk" site_id="4049" logo="https://d2n0069hmnqmmx.cloudfront.net/epgdata/1.0/newchanlogos/512/512/skychb4049.png">UK: SkySp News HD</channel>
  <channel site="sky.com" lang="en" xmltv_id="SkySportsNFL.uk" site_id="1333" logo="https://d2n0069hmnqmmx.cloudfront.net/epgdata/1.0/newchanlogos/512/512/skychb1333.png">UK: SkySp NFL</channel>
  <channel site="sky.com" lang="en" xmltv_id="SkySportsNFLHD.uk" site_id="4022" logo="https://d2n0069hmnqmmx.cloudfront.net/epgdata/1.0/newchanlogos/512/512/skychb4022.png">UK: SkySp NFL HD</channel>
  <channel site="sky.com" lang="en" xmltv_id="SkySportsPremierLeague.uk" site_id="1303" logo="https://d2n0069hmnqmmx.cloudfront.net/epgdata/1.0/newchanlogos/512/512/skychb1303.png">UK: SkySp PL</channel>
  <channel site="sky.com" lang="en" xmltv_id="SkySportsPremierLeagueHD.uk" site_id="4010" logo="https://d2n0069hmnqmmx.cloudfront.net/epgdata/1.0/newchanlogos/512/512/skychb4010.png">UK: SkySp PL HD</channel>
  <channel site="sky.com" lang="en" xmltv_id="SkySportsRacing.uk" site_id="1354" logo="https://d2n0069hmnqmmx.cloudfront.net/epgdata/1.0/newchanlogos/512/512/skychb1354.png">UK: SkySp Racing</channel>
  <channel site="sky.com" lang="en" xmltv_id="SkySportsRacingHD.uk" site_id="4032" logo="https://d2n0069hmnqmmx.cloudfront.net/epgdata/1.0/newchanlogos/512/512/skychb4032.png">UK: SkySp Racing HD</channel>
  <channel site="sky.com" lang="en" xmltv_id="SkySportsTennis.uk" site_id="1284" logo="https://d2n0069hmnqmmx.cloudfront.net/epgdata/1.0/newchanlogos/512/512/skychb1284.png">UK: SkySp Tennis</channel>
  <channel site="sky.com" lang="en" xmltv_id="SkyWitness.uk" site_id="2201" logo="https://d2n0069hmnqmmx.cloudfront.net/epgdata/1.0/newchanlogos/512/512/skychb2201.png">UK: Sky Witness</channel>
  <channel site="sky.com" lang="en" xmltv_id="SkyWitnessHD.uk" site_id="4066" logo="https://d2n0069hmnqmmx.cloudfront.net/epgdata/1.0/newchanlogos/512/512/skychb4066.png">UK: Sky Witness HD</channel>
  <channel site="sky.com" lang="en" xmltv_id="SkyWitnessPlus1.uk" site_id="2205" logo="https://d2n0069hmnqmmx.cloudfront.net/epgdata/1.0/newchanlogos/512/512/skychb2205.png">UK: Sky Witness+1</channel>
  <channel site="sky.com" lang="en" xmltv_id="SonyMax.uk" site_id="2603" logo="https://d2n0069hmnqmmx.cloudfront.net/epgdata/1.0/newchanlogos/512/512/skychb2603.png">UK: SONY MAX</channel>
  <channel site="sky.com" lang="en" xmltv_id="SonyMaxHD.uk" site_id="4046" logo="https://d2n0069hmnqmmx.cloudfront.net/epgdata/1.0/newchanlogos/512/512/skychb4046.png">UK: SONY MAX HD</channel>
  <channel site="sky.com" lang="en" xmltv_id="SportyStuffTV.uk" site_id="1223" logo="https://d2n0069hmnqmmx.cloudfront.net/epgdata/1.0/newchanlogos/512/512/skychb1223.png">UK: SportyStuff HD</channel>
  <channel site="sky.com" lang="en" xmltv_id="TalkingPicturesTV.uk" site_id="5252" logo="https://d2n0069hmnqmmx.cloudfront.net/epgdata/1.0/newchanlogos/512/512/skychb5252.png">UK: TalkingPictures</channel>
  <channel site="sky.com" lang="en" xmltv_id="TalkTV.uk" site_id="1078" logo="https://d2n0069hmnqmmx.cloudfront.net/epgdata/1.0/newchanlogos/512/512/skychb1078.png">UK: TalkTV HD</channel>
  <channel site="sky.com" lang="en" xmltv_id="TBNUK.uk" site_id="3109" logo="https://d2n0069hmnqmmx.cloudfront.net/epgdata/1.0/newchanlogos/512/512/skychb3109.png">UK: TBN UK</channel>
  <channel site="sky.com" lang="en" xmltv_id="Thats60s.uk" site_id="1134" logo="https://d2n0069hmnqmmx.cloudfront.net/epgdata/1.0/newchanlogos/512/512/skychb1134.png">UK: That's 60s</channel>
  <channel site="sky.com" lang="en" xmltv_id="Thats70s.uk" site_id="1311" logo="https://d2n0069hmnqmmx.cloudfront.net/epgdata/1.0/newchanlogos/512/512/skychb1311.png">UK: That's Christmas</channel>
  <channel site="sky.com" lang="en" xmltv_id="Thats90s.uk" site_id="1222" logo="https://d2n0069hmnqmmx.cloudfront.net/epgdata/1.0/newchanlogos/512/512/skychb1222.png">UK: That's 90s</channel>
  <channel site="sky.com" lang="en" xmltv_id="ThatsTV.uk" site_id="1017" logo="https://d2n0069hmnqmmx.cloudfront.net/epgdata/1.0/newchanlogos/512/512/skychb1017.png">UK: That's TV</channel>
  <channel site="sky.com" lang="en" xmltv_id="TheBox.uk" site_id="1802" logo="https://d2n0069hmnqmmx.cloudfront.net/epgdata/1.0/newchanlogos/512/512/skychb1802.png">UK: BoXmas</channel>
  <channel site="sky.com" lang="en" xmltv_id="TheWordNetwork.us" site_id="3205" logo="https://d2n0069hmnqmmx.cloudfront.net/epgdata/1.0/newchanlogos/512/512/skychb3205.png">UK: Word Network</channel>
  <channel site="sky.com" lang="en" xmltv_id="TinyPop.uk" site_id="3780" logo="https://d2n0069hmnqmmx.cloudfront.net/epgdata/1.0/newchanlogos/512/512/skychb3780.png">UK: Tiny Pop</channel>
  <channel site="sky.com" lang="en" xmltv_id="TinyPopPlus1.uk" site_id="4261" logo="https://d2n0069hmnqmmx.cloudfront.net/epgdata/1.0/newchanlogos/512/512/skychb4261.png">UK: Tiny Pop+1</channel>
  <channel site="sky.com" lang="en" xmltv_id="TJC.uk" site_id="1033" logo="https://d2n0069hmnqmmx.cloudfront.net/epgdata/1.0/newchanlogos/512/512/skychb1033.png">UK: TJC</channel>
  <channel site="sky.com" lang="en" xmltv_id="TJCHD.uk" site_id="1113" logo="https://d2n0069hmnqmmx.cloudfront.net/epgdata/1.0/newchanlogos/512/512/skychb1113.png">UK: TJC HD</channel>
  <channel site="sky.com" lang="en" xmltv_id="TLC.uk" site_id="5450" logo="https://d2n0069hmnqmmx.cloudfront.net/epgdata/1.0/newchanlogos/512/512/skychb5450.png">UK: TLC</channel>
  <channel site="sky.com" lang="en" xmltv_id="TLCHD.uk" site_id="3812" logo="https://d2n0069hmnqmmx.cloudfront.net/epgdata/1.0/newchanlogos/512/512/skychb3812.png">UK: TLC HD</channel>
  <channel site="sky.com" lang="en" xmltv_id="TLCPlus1.uk" site_id="5451" logo="https://d2n0069hmnqmmx.cloudfront.net/epgdata/1.0/newchanlogos/512/512/skychb5451.png">UK: TLC+1</channel>
  <channel site="sky.com" lang="en" xmltv_id="TNTSports1.uk" site_id="3625" logo="https://d2n0069hmnqmmx.cloudfront.net/epgdata/1.0/newchanlogos/512/512/skychb3625.png">UK: TNTSports1 HD</channel>
  <channel site="sky.com" lang="en" xmltv_id="TNTSports1.uk" site_id="3661" logo="https://d2n0069hmnqmmx.cloudfront.net/epgdata/1.0/newchanlogos/512/512/skychb3661.png">UK: TNT Sports 1</channel>
  <channel site="sky.com" lang="en" xmltv_id="TNTSports2.uk" site_id="3627" logo="https://d2n0069hmnqmmx.cloudfront.net/epgdata/1.0/newchanlogos/512/512/skychb3627.png">UK: TNTSports2 HD</channel>
  <channel site="sky.com" lang="en" xmltv_id="TNTSports2.uk" site_id="3663" logo="https://d2n0069hmnqmmx.cloudfront.net/epgdata/1.0/newchanlogos/512/512/skychb3663.png">UK: TNT Sports 2</channel>
  <channel site="sky.com" lang="en" xmltv_id="TNTSports3.uk" site_id="3629" logo="https://d2n0069hmnqmmx.cloudfront.net/epgdata/1.0/newchanlogos/512/512/skychb3629.png">UK: TNTSports3 HD</channel>
  <channel site="sky.com" lang="en" xmltv_id="TNTSports3.uk" site_id="5032" logo="https://d2n0069hmnqmmx.cloudfront.net/epgdata/1.0/newchanlogos/512/512/skychb5032.png">UK: TNT Sports 3</channel>
  <channel site="sky.com" lang="en" xmltv_id="TNTSports4.uk" site_id="3141" logo="https://d2n0069hmnqmmx.cloudfront.net/epgdata/1.0/newchanlogos/512/512/skychb3141.png">UK: TNT Sports 4</channel>
  <channel site="sky.com" lang="en" xmltv_id="TNTSports4HD.uk" site_id="4040" logo="https://d2n0069hmnqmmx.cloudfront.net/epgdata/1.0/newchanlogos/512/512/skychb4040.png">UK: TNTSports4 HD</channel>
  <channel site="sky.com" lang="en" xmltv_id="TNTSportsBoxOffice2.uk" site_id="1218" logo="https://d2n0069hmnqmmx.cloudfront.net/epgdata/1.0/newchanlogos/512/512/skychb1218.png">UK: TNTSBoxOff2HD</channel>
  <channel site="sky.com" lang="en" xmltv_id="TogetherTV.uk" site_id="1872" logo="https://d2n0069hmnqmmx.cloudfront.net/epgdata/1.0/newchanlogos/512/512/skychb1872.png">UK: Together</channel>
  <channel site="sky.com" lang="en" xmltv_id="TraceVault.uk" site_id="3935" logo="https://d2n0069hmnqmmx.cloudfront.net/epgdata/1.0/newchanlogos/512/512/skychb3935.png">UK: Trace Vault</channel>
  <channel site="sky.com" lang="en" xmltv_id="Travelxp.in" site_id="1226" logo="https://d2n0069hmnqmmx.cloudfront.net/epgdata/1.0/newchanlogos/512/512/skychb1226.png">UK: Travelxp</channel>
  <channel site="sky.com" lang="en" xmltv_id="TRTWorld.tr" site_id="5071" logo="https://d2n0069hmnqmmx.cloudfront.net/epgdata/1.0/newchanlogos/512/512/skychb5071.png">UK: TRT World</channel>
  <channel site="sky.com" lang="en" xmltv_id="TRTWorldHD.tr" site_id="5237" logo="https://d2n0069hmnqmmx.cloudfront.net/epgdata/1.0/newchanlogos/512/512/skychb5237.png">UK: TRT World HD</channel>
  <channel site="sky.com" lang="en" xmltv_id="TVCNews.ng" site_id="5882" logo="https://d2n0069hmnqmmx.cloudfront.net/epgdata/1.0/newchanlogos/512/512/skychb5882.png">UK: TVC News</channel>
  <channel site="sky.com" lang="en" xmltv_id="TVOne.uk" site_id="5426" logo="https://d2n0069hmnqmmx.cloudfront.net/epgdata/1.0/newchanlogos/512/512/skychb5426.png">UK: TV One</channel>
  <channel site="sky.com" lang="en" xmltv_id="TVWarehouse.uk" site_id="3632" logo="https://d2n0069hmnqmmx.cloudfront.net/epgdata/1.0/newchanlogos/512/512/skychb3632.png">UK: TV Warehouse</channel>
  <channel site="sky.com" lang="en" xmltv_id="UtsavGoldHD.in" site_id="4047" logo="https://d2n0069hmnqmmx.cloudfront.net/epgdata/1.0/newchanlogos/512/512/skychb4047.png">UK: Utsav Gold HD</channel>
  <channel site="sky.com" lang="en" xmltv_id="UtsavPlusHD.uk" site_id="5300" logo="https://d2n0069hmnqmmx.cloudfront.net/epgdata/1.0/newchanlogos/512/512/skychb5300.png">UK: Utsav Plus HD</channel>
  <channel site="sky.com" lang="en" xmltv_id="VenusTV.uk" site_id="3720" logo="https://d2n0069hmnqmmx.cloudfront.net/epgdata/1.0/newchanlogos/512/512/skychb3720.png">UK: Siraj TV</channel>
  <channel site="sky.com" lang="en" xmltv_id="ViaplaySports1.uk" site_id="1289" logo="https://d2n0069hmnqmmx.cloudfront.net/epgdata/1.0/newchanlogos/512/512/skychb1289.png">UK: Viaplay 1 HD</channel>
  <channel site="sky.com" lang="en" xmltv_id="ViaplaySports2.uk" site_id="1290" logo="https://d2n0069hmnqmmx.cloudfront.net/epgdata/1.0/newchanlogos/512/512/skychb1290.png">UK: Viaplay 2 HD</channel>
  <channel site="sky.com" lang="en" xmltv_id="ViaplayXtra.uk" site_id="1150" logo="https://d2n0069hmnqmmx.cloudfront.net/epgdata/1.0/newchanlogos/512/512/skychb1150.png">UK: ViaplayXtraHD</channel>
  <channel site="sky.com" lang="en" xmltv_id="W.uk" site_id="2617" logo="https://d2n0069hmnqmmx.cloudfront.net/epgdata/1.0/newchanlogos/512/512/skychb2617.png">UK: W</channel>
  <channel site="sky.com" lang="en" xmltv_id="WHD.uk" site_id="3810" logo="https://d2n0069hmnqmmx.cloudfront.net/epgdata/1.0/newchanlogos/512/512/skychb3810.png">UK: W HD</channel>
  <channel site="sky.com" lang="en" xmltv_id="WION.in" site_id="1084" logo="https://d2n0069hmnqmmx.cloudfront.net/epgdata/1.0/newchanlogos/512/512/skychb1084.png">UK: WION HD</channel>
  <channel site="sky.com" lang="en" xmltv_id="WPlus1.uk" site_id="2616" logo="https://d2n0069hmnqmmx.cloudfront.net/epgdata/1.0/newchanlogos/512/512/skychb2616.png">UK: W+1</channel>
  <channel site="sky.com" lang="en" xmltv_id="Yesterday.uk" site_id="2305" logo="https://d2n0069hmnqmmx.cloudfront.net/epgdata/1.0/newchanlogos/512/512/skychb2305.png">UK: YESTERDAY</channel>
  <channel site="sky.com" lang="en" xmltv_id="YesterdayHD.uk" site_id="1139" logo="https://d2n0069hmnqmmx.cloudfront.net/epgdata/1.0/newchanlogos/512/512/skychb1139.png">UK: YESTERDAY HD</channel>
  <channel site="sky.com" lang="en" xmltv_id="YesterdayPlus1.uk" site_id="2615" logo="https://d2n0069hmnqmmx.cloudfront.net/epgdata/1.0/newchanlogos/512/512/skychb2615.png">UK: YESTERDAY+1</channel>
  <channel site="sky.com" lang="en" xmltv_id="ZeeTVUK.uk" site_id="2607" logo="https://d2n0069hmnqmmx.cloudfront.net/epgdata/1.0/newchanlogos/512/512/skychb2607.png">UK: Zee TV</channel>
  <channel site="sky.com" lang="en" xmltv_id="92NewsHD.pk" site_id="3822" logo="https://d2n0069hmnqmmx.cloudfront.net/epgdata/1.0/newchanlogos/512/512/skychb3822.png">UK: 92 News</channel>
  <channel site="sky.com" lang="hi" xmltv_id="AajTak.in" site_id="3255" logo="https://d2n0069hmnqmmx.cloudfront.net/epgdata/1.0/newchanlogos/512/512/skychb3255.png">UK: AAJ TAK</channel>
  <channel site="sky.com" lang="en" xmltv_id="Aastha.in" site_id="3594" logo="https://d2n0069hmnqmmx.cloudfront.net/epgdata/1.0/newchanlogos/512/512/skychb3594.png">UK: Aastha</channel>
  <channel site="sky.com" lang="en" xmltv_id="ARYDigitalUK.uk" site_id="4265" logo="https://d2n0069hmnqmmx.cloudfront.net/epgdata/1.0/newchanlogos/512/512/skychb4265.png">UK: ARY Digital</channel>
  <channel site="sky.com" lang="en" xmltv_id="B4UMoviesUK.uk" site_id="5703" logo="https://d2n0069hmnqmmx.cloudfront.net/epgdata/1.0/newchanlogos/512/512/skychb5703.png">UK: B4U Movies</channel>
  <channel site="sky.com" lang="en" xmltv_id="B4UMusicUK.uk" site_id="5708" logo="https://d2n0069hmnqmmx.cloudfront.net/epgdata/1.0/newchanlogos/512/512/skychb5708.png">UK: B4U Music</channel>
  <channel site="sky.com" lang="en" xmltv_id="Colors.in" site_id="3714" logo="https://d2n0069hmnqmmx.cloudfront.net/epgdata/1.0/newchanlogos/512/512/skychb3714.png">UK: COLORS</channel>
  <channel site="sky.com" lang="en" xmltv_id="ColorsCineplex.in" site_id="1105" logo="https://d2n0069hmnqmmx.cloudfront.net/epgdata/1.0/newchanlogos/512/512/skychb1105.png">UK: ColorsCineplex</channel>
  <channel site="sky.com" lang="en" xmltv_id="ColorsGujarati.in" site_id="1090" logo="https://d2n0069hmnqmmx.cloudfront.net/epgdata/1.0/newchanlogos/512/512/skychb1090.png">UK: ColorsGujarati</channel>
  <channel site="sky.com" lang="en" xmltv_id="ColorsRishteyEurope.in" site_id="3916" logo="https://d2n0069hmnqmmx.cloudfront.net/epgdata/1.0/newchanlogos/512/512/skychb3916.png">UK: ColorsRishtey</channel>
  <channel site="sky.com" lang="en" xmltv_id="GeoUK.uk" site_id="4110" logo="https://d2n0069hmnqmmx.cloudfront.net/epgdata/1.0/newchanlogos/512/512/skychb4110.png">UK: GEO TV</channel>
  <channel site="sky.com" lang="en" xmltv_id="HumEurope.pk" site_id="5205" logo="https://d2n0069hmnqmmx.cloudfront.net/epgdata/1.0/newchanlogos/512/512/skychb5205.png">UK: HUM EUROPE</channel>
  <channel site="sky.com" lang="en" xmltv_id="IslamChannelUrdu.uk" site_id="5211" logo="https://d2n0069hmnqmmx.cloudfront.net/epgdata/1.0/newchanlogos/512/512/skychb5211.png">UK: Islam Ch Urdu</channel>
  <channel site="sky.com" lang="en" xmltv_id="MATVChannel.uk" site_id="3401" logo="https://d2n0069hmnqmmx.cloudfront.net/epgdata/1.0/newchanlogos/512/512/skychb3401.png">UK: MATV National</channel>
  <channel site="sky.com" lang="en" xmltv_id="SanskarTV.in" site_id="1100" logo="https://d2n0069hmnqmmx.cloudfront.net/epgdata/1.0/newchanlogos/512/512/skychb1100.png">UK: Sanskar</channel>
  <channel site="sky.com" lang="en" xmltv_id="SonyEntertainmentTelevisionAsia.in" site_id="4045" logo="https://d2n0069hmnqmmx.cloudfront.net/epgdata/1.0/newchanlogos/512/512/skychb4045.png">UK: SONY TV HD</channel>
  <channel site="sky.com" lang="en" xmltv_id="SonyMax2.in" site_id="5431" logo="https://d2n0069hmnqmmx.cloudfront.net/epgdata/1.0/newchanlogos/512/512/skychb5431.png">UK: SONY MAX 2</channel>
  <channel site="sky.com" lang="en" xmltv_id="SonySABAsia.in" site_id="3631" logo="https://d2n0069hmnqmmx.cloudfront.net/epgdata/1.0/newchanlogos/512/512/skychb3631.png">UK: SONY SAB</channel>
  <channel site="sky.com" lang="en" xmltv_id="TakbeerTV.uk" site_id="4408" logo="https://d2n0069hmnqmmx.cloudfront.net/epgdata/1.0/newchanlogos/512/512/skychb4408.png">UK: Takbeer TV</channel>
  <channel site="sky.com" lang="en" xmltv_id="UtsavBharat.uk" site_id="3608" logo="https://d2n0069hmnqmmx.cloudfront.net/epgdata/1.0/newchanlogos/512/512/skychb3608.png">UK: Utsav Bharat</channel>
  <channel site="sky.com" lang="en" xmltv_id="UtsavGold.in" site_id="3613" logo="https://d2n0069hmnqmmx.cloudfront.net/epgdata/1.0/newchanlogos/512/512/skychb3613.png">UK: Utsav Gold</channel>
  <channel site="sky.com" lang="en" xmltv_id="UtsavPlus.uk" site_id="1771" logo="https://d2n0069hmnqmmx.cloudfront.net/epgdata/1.0/newchanlogos/512/512/skychb1771.png">UK: Utsav Plus</channel>
  <channel site="sky.com" lang="en" xmltv_id="ZeeCinemaUK.uk" site_id="2608" logo="https://d2n0069hmnqmmx.cloudfront.net/epgdata/1.0/newchanlogos/512/512/skychb2608.png">UK: Zee Cinema</channel>
  <channel site="sky.com" lang="hi" xmltv_id="ZeeTVUK.uk" site_id="1016" logo="https://d2n0069hmnqmmx.cloudfront.net/epgdata/1.0/newchanlogos/512/512/skychb1016.png">UK: Zee TV HD</channel>
</channels>
